[{"Spike_D796Y": 0.0, "Spike_E484A": 0.0, "Spike_G339D": 0.0, "Spike_G446S": 0.0, "Spike_G496S": 0.0, "Spike_H69del": 0.0, "Spike_K417N": 0.0, "Spike_L452R": 0.0, "Spike_N440K": 0.0, "Spike_N501Y": 0.0, "Spike_P681R": 0.0, "Spike_Q493R": 0.0, "Spike_Q498R": 0.0, "Spike_R346K": 0.0, "Spike_S373P": 0.0, "Spike_S375F": 0.0, "Spike_S477N": 0.0, "Spike_T478K": 0.0, "Spike_V143del": 0.0, "Spike_V70del": 0.0, "Spike_Y144del": 0.0, "Spike_Y145H": 0.0, "Spike_Y505H": 0.0, "country": "Brazil", "date": "1 Mar 2020", "date_range": "1 Mar-8 Mar 2020", "submissions": 10.0}, {"Spike_D796Y": 0.0, "Spike_E484A": 0.0, "Spike_G339D": 0.0, "Spike_G446S": 0.0, "Spike_G496S": 0.0, "Spike_H69del": 0.0, "Spike_K417N": 0.0, "Spike_L452R": 0.0, "Spike_N440K": 0.0, "Spike_N501Y": 0.0, "Spike_P681R": 0.0, "Spike_Q493R": 0.0, "Spike_Q498R": 0.0, "Spike_R346K": 0.0, "Spike_S373P": 0.0, "Spike_S375F": 0.0, "Spike_S477N": 0.0, "Spike_T478K": 0.0, "Spike_V143del": 0.0, "Spike_V70del": 0.0, "Spike_Y144del": 0.0, "Spike_Y145H": 0.0, "Spike_Y505H": 0.0, "country": "Brazil", "date": "8 Mar 2020", "date_range": "8 Mar-15 Mar 2020", "submissions": 22.0}, {"Spike_D796Y": 0.0, "Spike_E484A": 0.0, "Spike_G339D": 0.0, "Spike_G446S": 0.0, "Spike_G496S": 0.0, "Spike_H69del": 0.0, "Spike_K417N": 0.0, "Spike_L452R": 0.0, "Spike_N440K": 0.0, "Spike_N501Y": 0.0, "Spike_P681R": 0.0, "Spike_Q493R": 0.0, "Spike_Q498R": 0.0, "Spike_R346K": 0.0, "Spike_S373P": 0.0, "Spike_S375F": 0.0, "Spike_S477N": 0.0, "Spike_T478K": 0.0, "Spike_V143del": 0.0, "Spike_V70del": 0.0, "Spike_Y144del": 0.0, "Spike_Y145H": 0.0, "Spike_Y505H": 0.0, "country": "Brazil", "date": "15 Mar 2020", "date_range": "15 Mar-22 Mar 2020", "submissions": 59.0}, {"Spike_D796Y": 0.0, "Spike_E484A": 0.0, "Spike_G339D": 0.0, "Spike_G446S": 0.0, "Spike_G496S": 0.0, "Spike_H69del": 0.0, "Spike_K417N": 0.0, "Spike_L452R": 0.0, "Spike_N440K": 0.0, "Spike_N501Y": 0.0, "Spike_P681R": 0.0, "Spike_Q493R": 0.0, "Spike_Q498R": 0.0, "Spike_R346K": 0.0, "Spike_S373P": 0.0, "Spike_S375F": 0.0, "Spike_S477N": 0.0, "Spike_T478K": 0.0, "Spike_V143del": 0.0, "Spike_V70del": 0.0, "Spike_Y144del": 0.0, "Spike_Y145H": 0.0, "Spike_Y505H": 0.0, "country": "Brazil", "date": "22 Mar 2020", "date_range": "22 Mar-29 Mar 2020", "submissions": 210.0}, {"Spike_D796Y": 0.0, "Spike_E484A": 0.0, "Spike_G339D": 0.0, "Spike_G446S": 0.0, "Spike_G496S": 0.0, "Spike_H69del": 0.0, "Spike_K417N": 0.0, "Spike_L452R": 0.0, "Spike_N440K": 0.0, "Spike_N501Y": 0.0, "Spike_P681R": 0.0, "Spike_Q493R": 0.0, "Spike_Q498R": 0.0, "Spike_R346K": 0.0, "Spike_S373P": 0.0, "Spike_S375F": 0.0, "Spike_S477N": 0.0, "Spike_T478K": 0.0, "Spike_V143del": 0.0, "Spike_V70del": 0.0, "Spike_Y144del": 0.0, "Spike_Y145H": 0.0, "Spike_Y505H": 0.0, "country": "Brazil", "date": "29 Mar 2020", "date_range": "29 Mar-5 Apr 2020", "submissions": 194.0}, {"Spike_D796Y": 0.0, "Spike_E484A": 0.0, "Spike_G339D": 0.0, "Spike_G446S": 0.0, "Spike_G496S": 0.0, "Spike_H69del": 0.0, "Spike_K417N": 0.0, "Spike_L452R": 0.0, "Spike_N440K": 0.0, "Spike_N501Y": 0.0, "Spike_P681R": 0.0, "Spike_Q493R": 0.0, "Spike_Q498R": 0.0, "Spike_R346K": 0.0, "Spike_S373P": 0.0, "Spike_S375F": 0.0, "Spike_S477N": 0.0, "Spike_T478K": 0.0, "Spike_V143del": 0.0, "Spike_V70del": 0.0, "Spike_Y144del": 0.0, "Spike_Y145H": 0.0, "Spike_Y505H": 0.0, "country": "Brazil", "date": "5 Apr 2020", "date_range": "5 Apr-12 Apr 2020", "submissions": 238.0}, {"Spike_D796Y": 0.0, "Spike_E484A": 0.0, "Spike_G339D": 0.0, "Spike_G446S": 0.0, "Spike_G496S": 0.0, "Spike_H69del": 0.0, "Spike_K417N": 0.0, "Spike_L452R": 0.0, "Spike_N440K": 0.0, "Spike_N501Y": 0.0045662100456621, "Spike_P681R": 0.0, "Spike_Q493R": 0.0, "Spike_Q498R": 0.0, "Spike_R346K": 0.0, "Spike_S373P": 0.0, "Spike_S375F": 0.0, "Spike_S477N": 0.0, "Spike_T478K": 0.0, "Spike_V143del": 0.0, "Spike_V70del": 0.0, "Spike_Y144del": 0.0, "Spike_Y145H": 0.0, "Spike_Y505H": 0.0, "country": "Brazil", "date": "12 Apr 2020", "date_range": "12 Apr-19 Apr 2020", "submissions": 219.0}, {"Spike_D796Y": 0.0, "Spike_E484A": 0.0, "Spike_G339D": 0.0, "Spike_G446S": 0.0, "Spike_G496S": 0.0, "Spike_H69del": 0.0, "Spike_K417N": 0.0, "Spike_L452R": 0.0, "Spike_N440K": 0.0, "Spike_N501Y": 0.0, "Spike_P681R": 0.0, "Spike_Q493R": 0.0, "Spike_Q498R": 0.0, "Spike_R346K": 0.0, "Spike_S373P": 0.0, "Spike_S375F": 0.0, "Spike_S477N": 0.0, "Spike_T478K": 0.0, "Spike_V143del": 0.0, "Spike_V70del": 0.0, "Spike_Y144del": 0.0, "Spike_Y145H": 0.0, "Spike_Y505H": 0.0, "country": "Brazil", "date": "19 Apr 2020", "date_range": "19 Apr-26 Apr 2020", "submissions": 287.0}, {"Spike_D796Y": 0.0, "Spike_E484A": 0.0, "Spike_G339D": 0.0, "Spike_G446S": 0.0, "Spike_G496S": 0.0, "Spike_H69del": 0.0, "Spike_K417N": 0.0, "Spike_L452R": 0.0, "Spike_N440K": 0.0, "Spike_N501Y": 0.0, "Spike_P681R": 0.0, "Spike_Q493R": 0.0, "Spike_Q498R": 0.0, "Spike_R346K": 0.0, "Spike_S373P": 0.0, "Spike_S375F": 0.0, "Spike_S477N": 0.0, "Spike_T478K": 0.0, "Spike_V143del": 0.0, "Spike_V70del": 0.0, "Spike_Y144del": 0.0, "Spike_Y145H": 0.0, "Spike_Y505H": 0.0, "country": "Brazil", "date": "26 Apr 2020", "date_range": "26 Apr-3 May 2020", "submissions": 310.0}, {"Spike_D796Y": 0.0, "Spike_E484A": 0.0, "Spike_G339D": 0.0, "Spike_G446S": 0.0, "Spike_G496S": 0.0, "Spike_H69del": 0.0, "Spike_K417N": 0.0, "Spike_L452R": 0.0, "Spike_N440K": 0.0, "Spike_N501Y": 0.0, "Spike_P681R": 0.0, "Spike_Q493R": 0.0, "Spike_Q498R": 0.0, "Spike_R346K": 0.0, "Spike_S373P": 0.0, "Spike_S375F": 0.0, "Spike_S477N": 0.0, "Spike_T478K": 0.0, "Spike_V143del": 0.0, "Spike_V70del": 0.0, "Spike_Y144del": 0.0, "Spike_Y145H": 0.0, "Spike_Y505H": 0.0, "country": "Brazil", "date": "3 May 2020", "date_range": "3 May-10 May 2020", "submissions": 183.0}, {"Spike_D796Y": 0.0, "Spike_E484A": 0.0, "Spike_G339D": 0.0, "Spike_G446S": 0.0, "Spike_G496S": 0.0, "Spike_H69del": 0.0, "Spike_K417N": 0.0, "Spike_L452R": 0.0, "Spike_N440K": 0.0, "Spike_N501Y": 0.0, "Spike_P681R": 0.0, "Spike_Q493R": 0.0, "Spike_Q498R": 0.0, "Spike_R346K": 0.0, "Spike_S373P": 0.0, "Spike_S375F": 0.0, "Spike_S477N": 0.0, "Spike_T478K": 0.0, "Spike_V143del": 0.0, "Spike_V70del": 0.0, "Spike_Y144del": 0.0, "Spike_Y145H": 0.0, "Spike_Y505H": 0.0, "country": "Brazil", "date": "10 May 2020", "date_range": "10 May-17 May 2020", "submissions": 129.0}, {"Spike_D796Y": 0.0, "Spike_E484A": 0.0, "Spike_G339D": 0.0, "Spike_G446S": 0.0, "Spike_G496S": 0.0, "Spike_H69del": 0.0, "Spike_K417N": 0.0, "Spike_L452R": 0.0, "Spike_N440K": 0.0, "Spike_N501Y": 0.0, "Spike_P681R": 0.0, "Spike_Q493R": 0.0, "Spike_Q498R": 0.0, "Spike_R346K": 0.0, "Spike_S373P": 0.0, "Spike_S375F": 0.0, "Spike_S477N": 0.0, "Spike_T478K": 0.0, "Spike_V143del": 0.008547008547008548, "Spike_V70del": 0.0, "Spike_Y144del": 0.008547008547008548, "Spike_Y145H": 0.0, "Spike_Y505H": 0.0, "country": "Brazil", "date": "17 May 2020", "date_range": "17 May-24 May 2020", "submissions": 117.0}, {"Spike_D796Y": 0.0, "Spike_E484A": 0.0, "Spike_G339D": 0.0, "Spike_G446S": 0.0, "Spike_G496S": 0.0, "Spike_H69del": 0.014084507042253521, "Spike_K417N": 0.0, "Spike_L452R": 0.0, "Spike_N440K": 0.0, "Spike_N501Y": 0.0, "Spike_P681R": 0.0, "Spike_Q493R": 0.0, "Spike_Q498R": 0.0, "Spike_R346K": 0.0, "Spike_S373P": 0.0, "Spike_S375F": 0.0, "Spike_S477N": 0.0, "Spike_T478K": 0.0, "Spike_V143del": 0.0, "Spike_V70del": 0.014084507042253521, "Spike_Y144del": 0.0, "Spike_Y145H": 0.0, "Spike_Y505H": 0.0, "country": "Brazil", "date": "24 May 2020", "date_range": "24 May-31 May 2020", "submissions": 71.0}, {"Spike_D796Y": 0.0, "Spike_E484A": 0.0, "Spike_G339D": 0.0, "Spike_G446S": 0.0, "Spike_G496S": 0.0, "Spike_H69del": 0.0, "Spike_K417N": 0.0, "Spike_L452R": 0.0, "Spike_N440K": 0.0, "Spike_N501Y": 0.0, "Spike_P681R": 0.0, "Spike_Q493R": 0.0, "Spike_Q498R": 0.0, "Spike_R346K": 0.0, "Spike_S373P": 0.0, "Spike_S375F": 0.0, "Spike_S477N": 0.0, "Spike_T478K": 0.0, "Spike_V143del": 0.0, "Spike_V70del": 0.0, "Spike_Y144del": 0.0, "Spike_Y145H": 0.0, "Spike_Y505H": 0.0, "country": "Brazil", "date": "31 May 2020", "date_range": "31 May-7 Jun 2020", "submissions": 76.0}, {"Spike_D796Y": 0.0, "Spike_E484A": 0.0, "Spike_G339D": 0.0, "Spike_G446S": 0.0, "Spike_G496S": 0.0, "Spike_H69del": 0.0, "Spike_K417N": 0.0, "Spike_L452R": 0.0, "Spike_N440K": 0.0, "Spike_N501Y": 0.0, "Spike_P681R": 0.0, "Spike_Q493R": 0.0, "Spike_Q498R": 0.0, "Spike_R346K": 0.0, "Spike_S373P": 0.0, "Spike_S375F": 0.0, "Spike_S477N": 0.0, "Spike_T478K": 0.0, "Spike_V143del": 0.0, "Spike_V70del": 0.0, "Spike_Y144del": 0.0, "Spike_Y145H": 0.0, "Spike_Y505H": 0.0, "country": "Brazil", "date": "7 Jun 2020", "date_range": "7 Jun-14 Jun 2020", "submissions": 125.0}, {"Spike_D796Y": 0.0, "Spike_E484A": 0.0, "Spike_G339D": 0.0, "Spike_G446S": 0.0, "Spike_G496S": 0.0, "Spike_H69del": 0.0, "Spike_K417N": 0.0, "Spike_L452R": 0.0, "Spike_N440K": 0.0, "Spike_N501Y": 0.010526315789473684, "Spike_P681R": 0.0, "Spike_Q493R": 0.0, "Spike_Q498R": 0.0, "Spike_R346K": 0.0, "Spike_S373P": 0.0, "Spike_S375F": 0.0, "Spike_S477N": 0.0, "Spike_T478K": 0.0, "Spike_V143del": 0.0, "Spike_V70del": 0.0, "Spike_Y144del": 0.010526315789473684, "Spike_Y145H": 0.0, "Spike_Y505H": 0.0, "country": "Brazil", "date": "14 Jun 2020", "date_range": "14 Jun-21 Jun 2020", "submissions": 95.0}, {"Spike_D796Y": 0.0, "Spike_E484A": 0.0, "Spike_G339D": 0.0, "Spike_G446S": 0.0, "Spike_G496S": 0.0, "Spike_H69del": 0.0, "Spike_K417N": 0.0, "Spike_L452R": 0.0, "Spike_N440K": 0.0, "Spike_N501Y": 0.0, "Spike_P681R": 0.0, "Spike_Q493R": 0.0, "Spike_Q498R": 0.0, "Spike_R346K": 0.010752688172043012, "Spike_S373P": 0.0, "Spike_S375F": 0.0, "Spike_S477N": 0.0, "Spike_T478K": 0.0, "Spike_V143del": 0.010752688172043012, "Spike_V70del": 0.0, "Spike_Y144del": 0.021505376344086023, "Spike_Y145H": 0.0, "Spike_Y505H": 0.0, "country": "Brazil", "date": "21 Jun 2020", "date_range": "21 Jun-28 Jun 2020", "submissions": 93.0}, {"Spike_D796Y": 0.0, "Spike_E484A": 0.0, "Spike_G339D": 0.0, "Spike_G446S": 0.0, "Spike_G496S": 0.0, "Spike_H69del": 0.0, "Spike_K417N": 0.007462686567164179, "Spike_L452R": 0.0, "Spike_N440K": 0.0, "Spike_N501Y": 0.007462686567164179, "Spike_P681R": 0.0, "Spike_Q493R": 0.0, "Spike_Q498R": 0.0, "Spike_R346K": 0.0, "Spike_S373P": 0.0, "Spike_S375F": 0.0, "Spike_S477N": 0.0, "Spike_T478K": 0.0, "Spike_V143del": 0.0, "Spike_V70del": 0.0, "Spike_Y144del": 0.007462686567164179, "Spike_Y145H": 0.0, "Spike_Y505H": 0.0, "country": "Brazil", "date": "28 Jun 2020", "date_range": "28 Jun-5 Jul 2020", "submissions": 134.0}, {"Spike_D796Y": 0.0, "Spike_E484A": 0.0, "Spike_G339D": 0.0, "Spike_G446S": 0.0, "Spike_G496S": 0.0, "Spike_H69del": 0.0, "Spike_K417N": 0.0, "Spike_L452R": 0.0, "Spike_N440K": 0.0, "Spike_N501Y": 0.0, "Spike_P681R": 0.0, "Spike_Q493R": 0.0, "Spike_Q498R": 0.0, "Spike_R346K": 0.0, "Spike_S373P": 0.0, "Spike_S375F": 0.0, "Spike_S477N": 0.0, "Spike_T478K": 0.0, "Spike_V143del": 0.0, "Spike_V70del": 0.0, "Spike_Y144del": 0.005291005291005291, "Spike_Y145H": 0.0, "Spike_Y505H": 0.0, "country": "Brazil", "date": "5 Jul 2020", "date_range": "5 Jul-12 Jul 2020", "submissions": 189.0}, {"Spike_D796Y": 0.0, "Spike_E484A": 0.0, "Spike_G339D": 0.0, "Spike_G446S": 0.0, "Spike_G496S": 0.0, "Spike_H69del": 0.0, "Spike_K417N": 0.0, "Spike_L452R": 0.0, "Spike_N440K": 0.0, "Spike_N501Y": 0.0, "Spike_P681R": 0.0, "Spike_Q493R": 0.0, "Spike_Q498R": 0.0, "Spike_R346K": 0.0, "Spike_S373P": 0.0, "Spike_S375F": 0.0, "Spike_S477N": 0.0, "Spike_T478K": 0.0, "Spike_V143del": 0.0, "Spike_V70del": 0.0, "Spike_Y144del": 0.0, "Spike_Y145H": 0.0, "Spike_Y505H": 0.0, "country": "Brazil", "date": "12 Jul 2020", "date_range": "12 Jul-19 Jul 2020", "submissions": 96.0}, {"Spike_D796Y": 0.0, "Spike_E484A": 0.0, "Spike_G339D": 0.0, "Spike_G446S": 0.0, "Spike_G496S": 0.0, "Spike_H69del": 0.0, "Spike_K417N": 0.0, "Spike_L452R": 0.0, "Spike_N440K": 0.0, "Spike_N501Y": 0.0, "Spike_P681R": 0.0, "Spike_Q493R": 0.0, "Spike_Q498R": 0.0, "Spike_R346K": 0.0, "Spike_S373P": 0.0, "Spike_S375F": 0.0, "Spike_S477N": 0.0, "Spike_T478K": 0.0, "Spike_V143del": 0.0, "Spike_V70del": 0.0, "Spike_Y144del": 0.0, "Spike_Y145H": 0.0, "Spike_Y505H": 0.0, "country": "Brazil", "date": "19 Jul 2020", "date_range": "19 Jul-26 Jul 2020", "submissions": 91.0}, {"Spike_D796Y": 0.0, "Spike_E484A": 0.0, "Spike_G339D": 0.0, "Spike_G446S": 0.0, "Spike_G496S": 0.0, "Spike_H69del": 0.0, "Spike_K417N": 0.0, "Spike_L452R": 0.0, "Spike_N440K": 0.0, "Spike_N501Y": 0.0, "Spike_P681R": 0.0, "Spike_Q493R": 0.0, "Spike_Q498R": 0.0, "Spike_R346K": 0.0, "Spike_S373P": 0.0, "Spike_S375F": 0.0, "Spike_S477N": 0.0, "Spike_T478K": 0.0, "Spike_V143del": 0.0, "Spike_V70del": 0.0, "Spike_Y144del": 0.0, "Spike_Y145H": 0.0, "Spike_Y505H": 0.0, "country": "Brazil", "date": "26 Jul 2020", "date_range": "26 Jul-2 Aug 2020", "submissions": 102.0}, {"Spike_D796Y": 0.0, "Spike_E484A": 0.0, "Spike_G339D": 0.0, "Spike_G446S": 0.0, "Spike_G496S": 0.0, "Spike_H69del": 0.0, "Spike_K417N": 0.0, "Spike_L452R": 0.0, "Spike_N440K": 0.0, "Spike_N501Y": 0.0, "Spike_P681R": 0.0, "Spike_Q493R": 0.0, "Spike_Q498R": 0.0, "Spike_R346K": 0.0, "Spike_S373P": 0.0, "Spike_S375F": 0.0, "Spike_S477N": 0.0, "Spike_T478K": 0.0, "Spike_V143del": 0.0, "Spike_V70del": 0.0, "Spike_Y144del": 0.0, "Spike_Y145H": 0.0, "Spike_Y505H": 0.0, "country": "Brazil", "date": "2 Aug 2020", "date_range": "2 Aug-9 Aug 2020", "submissions": 134.0}, {"Spike_D796Y": 0.0, "Spike_E484A": 0.0, "Spike_G339D": 0.0, "Spike_G446S": 0.0, "Spike_G496S": 0.0, "Spike_H69del": 0.0, "Spike_K417N": 0.0, "Spike_L452R": 0.0, "Spike_N440K": 0.0, "Spike_N501Y": 0.008333333333333333, "Spike_P681R": 0.0, "Spike_Q493R": 0.0, "Spike_Q498R": 0.0, "Spike_R346K": 0.0, "Spike_S373P": 0.0, "Spike_S375F": 0.0, "Spike_S477N": 0.008333333333333333, "Spike_T478K": 0.0, "Spike_V143del": 0.0, "Spike_V70del": 0.0, "Spike_Y144del": 0.008333333333333333, "Spike_Y145H": 0.0, "Spike_Y505H": 0.0, "country": "Brazil", "date": "9 Aug 2020", "date_range": "9 Aug-16 Aug 2020", "submissions": 120.0}, {"Spike_D796Y": 0.0, "Spike_E484A": 0.0, "Spike_G339D": 0.0, "Spike_G446S": 0.0, "Spike_G496S": 0.0, "Spike_H69del": 0.0, "Spike_K417N": 0.0, "Spike_L452R": 0.0, "Spike_N440K": 0.0, "Spike_N501Y": 0.0, "Spike_P681R": 0.0, "Spike_Q493R": 0.0, "Spike_Q498R": 0.0, "Spike_R346K": 0.0, "Spike_S373P": 0.0, "Spike_S375F": 0.0, "Spike_S477N": 0.0, "Spike_T478K": 0.0, "Spike_V143del": 0.0, "Spike_V70del": 0.0, "Spike_Y144del": 0.0, "Spike_Y145H": 0.0, "Spike_Y505H": 0.0, "country": "Brazil", "date": "16 Aug 2020", "date_range": "16 Aug-23 Aug 2020", "submissions": 139.0}, {"Spike_D796Y": 0.0, "Spike_E484A": 0.0, "Spike_G339D": 0.0, "Spike_G446S": 0.0, "Spike_G496S": 0.0, "Spike_H69del": 0.0, "Spike_K417N": 0.0, "Spike_L452R": 0.0, "Spike_N440K": 0.0, "Spike_N501Y": 0.0, "Spike_P681R": 0.0, "Spike_Q493R": 0.0, "Spike_Q498R": 0.0, "Spike_R346K": 0.0, "Spike_S373P": 0.0, "Spike_S375F": 0.0, "Spike_S477N": 0.0, "Spike_T478K": 0.0, "Spike_V143del": 0.0, "Spike_V70del": 0.0, "Spike_Y144del": 0.0, "Spike_Y145H": 0.0, "Spike_Y505H": 0.0, "country": "Brazil", "date": "23 Aug 2020", "date_range": "23 Aug-30 Aug 2020", "submissions": 108.0}, {"Spike_D796Y": 0.0, "Spike_E484A": 0.0, "Spike_G339D": 0.0, "Spike_G446S": 0.0, "Spike_G496S": 0.0, "Spike_H69del": 0.0, "Spike_K417N": 0.0, "Spike_L452R": 0.0, "Spike_N440K": 0.0, "Spike_N501Y": 0.01098901098901099, "Spike_P681R": 0.0, "Spike_Q493R": 0.0, "Spike_Q498R": 0.0, "Spike_R346K": 0.0, "Spike_S373P": 0.0, "Spike_S375F": 0.0, "Spike_S477N": 0.0, "Spike_T478K": 0.0, "Spike_V143del": 0.0, "Spike_V70del": 0.0, "Spike_Y144del": 0.0, "Spike_Y145H": 0.0, "Spike_Y505H": 0.0, "country": "Brazil", "date": "30 Aug 2020", "date_range": "30 Aug-6 Sep 2020", "submissions": 91.0}, {"Spike_D796Y": 0.0, "Spike_E484A": 0.0, "Spike_G339D": 0.0, "Spike_G446S": 0.0, "Spike_G496S": 0.0, "Spike_H69del": 0.0, "Spike_K417N": 0.0, "Spike_L452R": 0.0, "Spike_N440K": 0.0, "Spike_N501Y": 0.0, "Spike_P681R": 0.0, "Spike_Q493R": 0.0, "Spike_Q498R": 0.0, "Spike_R346K": 0.0, "Spike_S373P": 0.0, "Spike_S375F": 0.0, "Spike_S477N": 0.014184397163120567, "Spike_T478K": 0.0, "Spike_V143del": 0.0, "Spike_V70del": 0.0, "Spike_Y144del": 0.0, "Spike_Y145H": 0.0, "Spike_Y505H": 0.0, "country": "Brazil", "date": "6 Sep 2020", "date_range": "6 Sep-13 Sep 2020", "submissions": 141.0}, {"Spike_D796Y": 0.0, "Spike_E484A": 0.0, "Spike_G339D": 0.0, "Spike_G446S": 0.0, "Spike_G496S": 0.0, "Spike_H69del": 0.0, "Spike_K417N": 0.0, "Spike_L452R": 0.0, "Spike_N440K": 0.0, "Spike_N501Y": 0.0, "Spike_P681R": 0.0, "Spike_Q493R": 0.0, "Spike_Q498R": 0.0, "Spike_R346K": 0.0, "Spike_S373P": 0.0, "Spike_S375F": 0.0, "Spike_S477N": 0.0, "Spike_T478K": 0.0, "Spike_V143del": 0.0, "Spike_V70del": 0.0, "Spike_Y144del": 0.0, "Spike_Y145H": 0.0, "Spike_Y505H": 0.0, "country": "Brazil", "date": "13 Sep 2020", "date_range": "13 Sep-20 Sep 2020", "submissions": 122.0}, {"Spike_D796Y": 0.0, "Spike_E484A": 0.0, "Spike_G339D": 0.0, "Spike_G446S": 0.0, "Spike_G496S": 0.0, "Spike_H69del": 0.0, "Spike_K417N": 0.0, "Spike_L452R": 0.0, "Spike_N440K": 0.0, "Spike_N501Y": 0.0, "Spike_P681R": 0.0, "Spike_Q493R": 0.0, "Spike_Q498R": 0.0, "Spike_R346K": 0.0, "Spike_S373P": 0.0, "Spike_S375F": 0.0, "Spike_S477N": 0.008130081300813009, "Spike_T478K": 0.0, "Spike_V143del": 0.0, "Spike_V70del": 0.0, "Spike_Y144del": 0.0, "Spike_Y145H": 0.0, "Spike_Y505H": 0.0, "country": "Brazil", "date": "20 Sep 2020", "date_range": "20 Sep-27 Sep 2020", "submissions": 123.0}, {"Spike_D796Y": 0.01, "Spike_E484A": 0.0, "Spike_G339D": 0.0, "Spike_G446S": 0.0, "Spike_G496S": 0.0, "Spike_H69del": 0.0, "Spike_K417N": 0.0, "Spike_L452R": 0.0, "Spike_N440K": 0.0, "Spike_N501Y": 0.0, "Spike_P681R": 0.0, "Spike_Q493R": 0.0, "Spike_Q498R": 0.0, "Spike_R346K": 0.0, "Spike_S373P": 0.0, "Spike_S375F": 0.0, "Spike_S477N": 0.0, "Spike_T478K": 0.0, "Spike_V143del": 0.0, "Spike_V70del": 0.0, "Spike_Y144del": 0.0, "Spike_Y145H": 0.0, "Spike_Y505H": 0.0, "country": "Brazil", "date": "27 Sep 2020", "date_range": "27 Sep-4 Oct 2020", "submissions": 100.0}, {"Spike_D796Y": 0.008, "Spike_E484A": 0.0, "Spike_G339D": 0.0, "Spike_G446S": 0.0, "Spike_G496S": 0.0, "Spike_H69del": 0.0, "Spike_K417N": 0.0, "Spike_L452R": 0.0, "Spike_N440K": 0.0, "Spike_N501Y": 0.008, "Spike_P681R": 0.0, "Spike_Q493R": 0.0, "Spike_Q498R": 0.0, "Spike_R346K": 0.0, "Spike_S373P": 0.0, "Spike_S375F": 0.0, "Spike_S477N": 0.008, "Spike_T478K": 0.0, "Spike_V143del": 0.0, "Spike_V70del": 0.0, "Spike_Y144del": 0.008, "Spike_Y145H": 0.0, "Spike_Y505H": 0.0, "country": "Brazil", "date": "4 Oct 2020", "date_range": "4 Oct-11 Oct 2020", "submissions": 125.0}, {"Spike_D796Y": 0.0, "Spike_E484A": 0.0, "Spike_G339D": 0.0, "Spike_G446S": 0.0, "Spike_G496S": 0.0, "Spike_H69del": 0.0, "Spike_K417N": 0.0, "Spike_L452R": 0.0, "Spike_N440K": 0.0, "Spike_N501Y": 0.0, "Spike_P681R": 0.0, "Spike_Q493R": 0.0, "Spike_Q498R": 0.0, "Spike_R346K": 0.0, "Spike_S373P": 0.0, "Spike_S375F": 0.0, "Spike_S477N": 0.0, "Spike_T478K": 0.0, "Spike_V143del": 0.0, "Spike_V70del": 0.0, "Spike_Y144del": 0.00909090909090909, "Spike_Y145H": 0.0, "Spike_Y505H": 0.0, "country": "Brazil", "date": "11 Oct 2020", "date_range": "11 Oct-18 Oct 2020", "submissions": 110.0}, {"Spike_D796Y": 0.0, "Spike_E484A": 0.0, "Spike_G339D": 0.0, "Spike_G446S": 0.0, "Spike_G496S": 0.0, "Spike_H69del": 0.0, "Spike_K417N": 0.0, "Spike_L452R": 0.0, "Spike_N440K": 0.0, "Spike_N501Y": 0.007352941176470588, "Spike_P681R": 0.0, "Spike_Q493R": 0.0, "Spike_Q498R": 0.0, "Spike_R346K": 0.0, "Spike_S373P": 0.0, "Spike_S375F": 0.0, "Spike_S477N": 0.022058823529411766, "Spike_T478K": 0.0, "Spike_V143del": 0.0, "Spike_V70del": 0.0, "Spike_Y144del": 0.0, "Spike_Y145H": 0.0, "Spike_Y505H": 0.0, "country": "Brazil", "date": "18 Oct 2020", "date_range": "18 Oct-25 Oct 2020", "submissions": 136.0}, {"Spike_D796Y": 0.0, "Spike_E484A": 0.0, "Spike_G339D": 0.0, "Spike_G446S": 0.0, "Spike_G496S": 0.0, "Spike_H69del": 0.0, "Spike_K417N": 0.0, "Spike_L452R": 0.0, "Spike_N440K": 0.0, "Spike_N501Y": 0.008771929824561403, "Spike_P681R": 0.0, "Spike_Q493R": 0.0, "Spike_Q498R": 0.0, "Spike_R346K": 0.0, "Spike_S373P": 0.0, "Spike_S375F": 0.0, "Spike_S477N": 0.043859649122807015, "Spike_T478K": 0.0, "Spike_V143del": 0.0, "Spike_V70del": 0.0, "Spike_Y144del": 0.0, "Spike_Y145H": 0.0, "Spike_Y505H": 0.0, "country": "Brazil", "date": "25 Oct 2020", "date_range": "25 Oct-1 Nov 2020", "submissions": 114.0}, {"Spike_D796Y": 0.0, "Spike_E484A": 0.0, "Spike_G339D": 0.0, "Spike_G446S": 0.0, "Spike_G496S": 0.0, "Spike_H69del": 0.0, "Spike_K417N": 0.0, "Spike_L452R": 0.0, "Spike_N440K": 0.0, "Spike_N501Y": 0.015503875968992248, "Spike_P681R": 0.0, "Spike_Q493R": 0.0, "Spike_Q498R": 0.0, "Spike_R346K": 0.0, "Spike_S373P": 0.0, "Spike_S375F": 0.0, "Spike_S477N": 0.0, "Spike_T478K": 0.0, "Spike_V143del": 0.0, "Spike_V70del": 0.0, "Spike_Y144del": 0.0, "Spike_Y145H": 0.0, "Spike_Y505H": 0.0, "country": "Brazil", "date": "1 Nov 2020", "date_range": "1 Nov-8 Nov 2020", "submissions": 129.0}, {"Spike_D796Y": 0.0, "Spike_E484A": 0.0, "Spike_G339D": 0.0, "Spike_G446S": 0.0, "Spike_G496S": 0.0, "Spike_H69del": 0.0, "Spike_K417N": 0.0, "Spike_L452R": 0.0, "Spike_N440K": 0.0, "Spike_N501Y": 0.013605442176870748, "Spike_P681R": 0.0, "Spike_Q493R": 0.0, "Spike_Q498R": 0.0, "Spike_R346K": 0.0, "Spike_S373P": 0.0, "Spike_S375F": 0.0, "Spike_S477N": 0.0, "Spike_T478K": 0.013605442176870748, "Spike_V143del": 0.0, "Spike_V70del": 0.0, "Spike_Y144del": 0.006802721088435374, "Spike_Y145H": 0.0, "Spike_Y505H": 0.0, "country": "Brazil", "date": "8 Nov 2020", "date_range": "8 Nov-15 Nov 2020", "submissions": 147.0}, {"Spike_D796Y": 0.0, "Spike_E484A": 0.0, "Spike_G339D": 0.0, "Spike_G446S": 0.0, "Spike_G496S": 0.0, "Spike_H69del": 0.0, "Spike_K417N": 0.0, "Spike_L452R": 0.0, "Spike_N440K": 0.0, "Spike_N501Y": 0.0, "Spike_P681R": 0.0, "Spike_Q493R": 0.0, "Spike_Q498R": 0.0, "Spike_R346K": 0.0, "Spike_S373P": 0.0, "Spike_S375F": 0.0, "Spike_S477N": 0.0, "Spike_T478K": 0.0, "Spike_V143del": 0.0, "Spike_V70del": 0.0, "Spike_Y144del": 0.012422360248447204, "Spike_Y145H": 0.0, "Spike_Y505H": 0.0, "country": "Brazil", "date": "15 Nov 2020", "date_range": "15 Nov-22 Nov 2020", "submissions": 161.0}, {"Spike_D796Y": 0.0, "Spike_E484A": 0.0, "Spike_G339D": 0.0, "Spike_G446S": 0.0, "Spike_G496S": 0.0, "Spike_H69del": 0.0, "Spike_K417N": 0.0, "Spike_L452R": 0.0, "Spike_N440K": 0.0, "Spike_N501Y": 0.008438818565400843, "Spike_P681R": 0.0, "Spike_Q493R": 0.0, "Spike_Q498R": 0.0, "Spike_R346K": 0.0, "Spike_S373P": 0.0, "Spike_S375F": 0.0, "Spike_S477N": 0.0, "Spike_T478K": 0.0, "Spike_V143del": 0.0, "Spike_V70del": 0.0, "Spike_Y144del": 0.016877637130801686, "Spike_Y145H": 0.0, "Spike_Y505H": 0.0, "country": "Brazil", "date": "22 Nov 2020", "date_range": "22 Nov-29 Nov 2020", "submissions": 237.0}, {"Spike_D796Y": 0.0029498525073746312, "Spike_E484A": 0.0, "Spike_G339D": 0.0, "Spike_G446S": 0.0, "Spike_G496S": 0.0, "Spike_H69del": 0.0, "Spike_K417N": 0.0, "Spike_L452R": 0.0, "Spike_N440K": 0.0, "Spike_N501Y": 0.0, "Spike_P681R": 0.0, "Spike_Q493R": 0.0, "Spike_Q498R": 0.0, "Spike_R346K": 0.0, "Spike_S373P": 0.0, "Spike_S375F": 0.0, "Spike_S477N": 0.008849557522123894, "Spike_T478K": 0.0, "Spike_V143del": 0.0, "Spike_V70del": 0.0, "Spike_Y144del": 0.0029498525073746312, "Spike_Y145H": 0.0, "Spike_Y505H": 0.0, "country": "Brazil", "date": "29 Nov 2020", "date_range": "29 Nov-6 Dec 2020", "submissions": 339.0}, {"Spike_D796Y": 0.0, "Spike_E484A": 0.0, "Spike_G339D": 0.0, "Spike_G446S": 0.0, "Spike_G496S": 0.0, "Spike_H69del": 0.0, "Spike_K417N": 0.0, "Spike_L452R": 0.004694835680751174, "Spike_N440K": 0.0, "Spike_N501Y": 0.018779342723004695, "Spike_P681R": 0.0, "Spike_Q493R": 0.0, "Spike_Q498R": 0.0, "Spike_R346K": 0.0, "Spike_S373P": 0.0, "Spike_S375F": 0.0, "Spike_S477N": 0.004694835680751174, "Spike_T478K": 0.0, "Spike_V143del": 0.0, "Spike_V70del": 0.0, "Spike_Y144del": 0.0, "Spike_Y145H": 0.0, "Spike_Y505H": 0.0, "country": "Brazil", "date": "6 Dec 2020", "date_range": "6 Dec-13 Dec 2020", "submissions": 213.0}, {"Spike_D796Y": 0.0, "Spike_E484A": 0.0, "Spike_G339D": 0.0, "Spike_G446S": 0.0, "Spike_G496S": 0.0, "Spike_H69del": 0.0, "Spike_K417N": 0.0, "Spike_L452R": 0.0, "Spike_N440K": 0.0, "Spike_N501Y": 0.004366812227074236, "Spike_P681R": 0.0, "Spike_Q493R": 0.0, "Spike_Q498R": 0.0, "Spike_R346K": 0.0, "Spike_S373P": 0.0, "Spike_S375F": 0.0, "Spike_S477N": 0.004366812227074236, "Spike_T478K": 0.0, "Spike_V143del": 0.0, "Spike_V70del": 0.0, "Spike_Y144del": 0.0, "Spike_Y145H": 0.0, "Spike_Y505H": 0.0, "country": "Brazil", "date": "13 Dec 2020", "date_range": "13 Dec-20 Dec 2020", "submissions": 229.0}, {"Spike_D796Y": 0.0035971223021582736, "Spike_E484A": 0.0, "Spike_G339D": 0.0, "Spike_G446S": 0.0, "Spike_G496S": 0.0, "Spike_H69del": 0.0, "Spike_K417N": 0.0, "Spike_L452R": 0.0035971223021582736, "Spike_N440K": 0.0, "Spike_N501Y": 0.050359712230215826, "Spike_P681R": 0.0, "Spike_Q493R": 0.0, "Spike_Q498R": 0.0, "Spike_R346K": 0.0, "Spike_S373P": 0.0, "Spike_S375F": 0.0, "Spike_S477N": 0.0035971223021582736, "Spike_T478K": 0.0, "Spike_V143del": 0.0, "Spike_V70del": 0.0, "Spike_Y144del": 0.0035971223021582736, "Spike_Y145H": 0.0, "Spike_Y505H": 0.0, "country": "Brazil", "date": "20 Dec 2020", "date_range": "20 Dec-27 Dec 2020", "submissions": 278.0}, {"Spike_D796Y": 0.0, "Spike_E484A": 0.0, "Spike_G339D": 0.0, "Spike_G446S": 0.0, "Spike_G496S": 0.0, "Spike_H69del": 0.014336917562724014, "Spike_K417N": 0.0, "Spike_L452R": 0.0, "Spike_N440K": 0.0, "Spike_N501Y": 0.17204301075268819, "Spike_P681R": 0.0, "Spike_Q493R": 0.0, "Spike_Q498R": 0.0, "Spike_R346K": 0.0, "Spike_S373P": 0.0, "Spike_S375F": 0.0, "Spike_S477N": 0.0035842293906810036, "Spike_T478K": 0.0, "Spike_V143del": 0.0, "Spike_V70del": 0.014336917562724014, "Spike_Y144del": 0.014336917562724014, "Spike_Y145H": 0.0, "Spike_Y505H": 0.0, "country": "Brazil", "date": "27 Dec 2020", "date_range": "27 Dec-3 Jan 2021", "submissions": 279.0}, {"Spike_D796Y": 0.0030120481927710845, "Spike_E484A": 0.0, "Spike_G339D": 0.0030120481927710845, "Spike_G446S": 0.0, "Spike_G496S": 0.0, "Spike_H69del": 0.009036144578313253, "Spike_K417N": 0.0, "Spike_L452R": 0.015060240963855422, "Spike_N440K": 0.0, "Spike_N501Y": 0.1686746987951807, "Spike_P681R": 0.0, "Spike_Q493R": 0.0, "Spike_Q498R": 0.0, "Spike_R346K": 0.0, "Spike_S373P": 0.0, "Spike_S375F": 0.0, "Spike_S477N": 0.0, "Spike_T478K": 0.0030120481927710845, "Spike_V143del": 0.012048192771084338, "Spike_V70del": 0.009036144578313253, "Spike_Y144del": 0.02108433734939759, "Spike_Y145H": 0.0, "Spike_Y505H": 0.0, "country": "Brazil", "date": "3 Jan 2021", "date_range": "3 Jan-10 Jan 2021", "submissions": 332.0}, {"Spike_D796Y": 0.005545286506469501, "Spike_E484A": 0.0, "Spike_G339D": 0.0, "Spike_G446S": 0.0, "Spike_G496S": 0.0, "Spike_H69del": 0.027726432532347505, "Spike_K417N": 0.0, "Spike_L452R": 0.0036968576709796672, "Spike_N440K": 0.0, "Spike_N501Y": 0.14602587800369685, "Spike_P681R": 0.0018484288354898336, "Spike_Q493R": 0.0, "Spike_Q498R": 0.0, "Spike_R346K": 0.0, "Spike_S373P": 0.0, "Spike_S375F": 0.0, "Spike_S477N": 0.0073937153419593345, "Spike_T478K": 0.0, "Spike_V143del": 0.011090573012939002, "Spike_V70del": 0.024029574861367836, "Spike_Y144del": 0.04066543438077634, "Spike_Y145H": 0.0, "Spike_Y505H": 0.0, "country": "Brazil", "date": "10 Jan 2021", "date_range": "10 Jan-17 Jan 2021", "submissions": 541.0}, {"Spike_D796Y": 0.006085192697768763, "Spike_E484A": 0.0, "Spike_G339D": 0.0, "Spike_G446S": 0.0, "Spike_G496S": 0.0, "Spike_H69del": 0.034482758620689655, "Spike_K417N": 0.0, "Spike_L452R": 0.004056795131845842, "Spike_N440K": 0.0, "Spike_N501Y": 0.20689655172413793, "Spike_P681R": 0.0, "Spike_Q493R": 0.0, "Spike_Q498R": 0.0, "Spike_R346K": 0.0, "Spike_S373P": 0.0, "Spike_S375F": 0.0, "Spike_S477N": 0.0, "Spike_T478K": 0.002028397565922921, "Spike_V143del": 0.006085192697768763, "Spike_V70del": 0.032454361054766734, "Spike_Y144del": 0.056795131845841784, "Spike_Y145H": 0.0, "Spike_Y505H": 0.0, "country": "Brazil", "date": "17 Jan 2021", "date_range": "17 Jan-24 Jan 2021", "submissions": 493.0}, {"Spike_D796Y": 0.002028397565922921, "Spike_E484A": 0.0, "Spike_G339D": 0.0, "Spike_G446S": 0.0, "Spike_G496S": 0.0, "Spike_H69del": 0.02636916835699797, "Spike_K417N": 0.0, "Spike_L452R": 0.002028397565922921, "Spike_N440K": 0.0, "Spike_N501Y": 0.30425963488843816, "Spike_P681R": 0.0, "Spike_Q493R": 0.0, "Spike_Q498R": 0.0, "Spike_R346K": 0.0, "Spike_S373P": 0.0, "Spike_S375F": 0.0, "Spike_S477N": 0.004056795131845842, "Spike_T478K": 0.002028397565922921, "Spike_V143del": 0.002028397565922921, "Spike_V70del": 0.02434077079107505, "Spike_Y144del": 0.038539553752535496, "Spike_Y145H": 0.0, "Spike_Y505H": 0.0, "country": "Brazil", "date": "24 Jan 2021", "date_range": "24 Jan-31 Jan 2021", "submissions": 493.0}, {"Spike_D796Y": 0.0, "Spike_E484A": 0.0, "Spike_G339D": 0.0, "Spike_G446S": 0.0, "Spike_G496S": 0.0, "Spike_H69del": 0.020491803278688523, "Spike_K417N": 0.0, "Spike_L452R": 0.004098360655737705, "Spike_N440K": 0.0, "Spike_N501Y": 0.3155737704918033, "Spike_P681R": 0.0, "Spike_Q493R": 0.0, "Spike_Q498R": 0.0, "Spike_R346K": 0.0, "Spike_S373P": 0.0, "Spike_S375F": 0.0, "Spike_S477N": 0.0, "Spike_T478K": 0.004098360655737705, "Spike_V143del": 0.010245901639344262, "Spike_V70del": 0.020491803278688523, "Spike_Y144del": 0.02663934426229508, "Spike_Y145H": 0.0, "Spike_Y505H": 0.0, "country": "Brazil", "date": "31 Jan 2021", "date_range": "31 Jan-7 Feb 2021", "submissions": 488.0}, {"Spike_D796Y": 0.0, "Spike_E484A": 0.0, "Spike_G339D": 0.0, "Spike_G446S": 0.0, "Spike_G496S": 0.0, "Spike_H69del": 0.01461038961038961, "Spike_K417N": 0.0, "Spike_L452R": 0.003246753246753247, "Spike_N440K": 0.0, "Spike_N501Y": 0.3522727272727273, "Spike_P681R": 0.0016233766233766235, "Spike_Q493R": 0.0, "Spike_Q498R": 0.0, "Spike_R346K": 0.0016233766233766235, "Spike_S373P": 0.0016233766233766235, "Spike_S375F": 0.0, "Spike_S477N": 0.008116883116883116, "Spike_T478K": 0.0016233766233766235, "Spike_V143del": 0.00974025974025974, "Spike_V70del": 0.01461038961038961, "Spike_Y144del": 0.01948051948051948, "Spike_Y145H": 0.0, "Spike_Y505H": 0.0, "country": "Brazil", "date": "7 Feb 2021", "date_range": "7 Feb-14 Feb 2021", "submissions": 616.0}, {"Spike_D796Y": 0.0, "Spike_E484A": 0.0, "Spike_G339D": 0.0, "Spike_G446S": 0.0, "Spike_G496S": 0.0, "Spike_H69del": 0.02130681818181818, "Spike_K417N": 0.0, "Spike_L452R": 0.007102272727272727, "Spike_N440K": 0.0, "Spike_N501Y": 0.46448863636363635, "Spike_P681R": 0.0014204545454545455, "Spike_Q493R": 0.0, "Spike_Q498R": 0.0, "Spike_R346K": 0.0014204545454545455, "Spike_S373P": 0.0, "Spike_S375F": 0.0, "Spike_S477N": 0.004261363636363636, "Spike_T478K": 0.002840909090909091, "Spike_V143del": 0.004261363636363636, "Spike_V70del": 0.02130681818181818, "Spike_Y144del": 0.026988636363636364, "Spike_Y145H": 0.0, "Spike_Y505H": 0.0, "country": "Brazil", "date": "14 Feb 2021", "date_range": "14 Feb-21 Feb 2021", "submissions": 704.0}, {"Spike_D796Y": 0.0, "Spike_E484A": 0.0, "Spike_G339D": 0.0, "Spike_G446S": 0.0, "Spike_G496S": 0.0, "Spike_H69del": 0.0352760736196319, "Spike_K417N": 0.0, "Spike_L452R": 0.007668711656441718, "Spike_N440K": 0.0, "Spike_N501Y": 0.6779141104294478, "Spike_P681R": 0.0015337423312883436, "Spike_Q493R": 0.0, "Spike_Q498R": 0.0, "Spike_R346K": 0.0, "Spike_S373P": 0.0, "Spike_S375F": 0.0, "Spike_S477N": 0.010736196319018405, "Spike_T478K": 0.0, "Spike_V143del": 0.007668711656441718, "Spike_V70del": 0.0352760736196319, "Spike_Y144del": 0.04141104294478527, "Spike_Y145H": 0.0, "Spike_Y505H": 0.0, "country": "Brazil", "date": "21 Feb 2021", "date_range": "21 Feb-28 Feb 2021", "submissions": 652.0}, {"Spike_D796Y": 0.001, "Spike_E484A": 0.0, "Spike_G339D": 0.0, "Spike_G446S": 0.0, "Spike_G496S": 0.0, "Spike_H69del": 0.021, "Spike_K417N": 0.0, "Spike_L452R": 0.0, "Spike_N440K": 0.0, "Spike_N501Y": 0.731, "Spike_P681R": 0.0, "Spike_Q493R": 0.0, "Spike_Q498R": 0.0, "Spike_R346K": 0.0, "Spike_S373P": 0.0, "Spike_S375F": 0.0, "Spike_S477N": 0.004, "Spike_T478K": 0.0, "Spike_V143del": 0.002, "Spike_V70del": 0.021, "Spike_Y144del": 0.021, "Spike_Y145H": 0.0, "Spike_Y505H": 0.0, "country": "Brazil", "date": "28 Feb 2021", "date_range": "28 Feb-7 Mar 2021", "submissions": 1000.0}, {"Spike_D796Y": 0.004424778761061947, "Spike_E484A": 0.0, "Spike_G339D": 0.0, "Spike_G446S": 0.0, "Spike_G496S": 0.0, "Spike_H69del": 0.02765486725663717, "Spike_K417N": 0.00663716814159292, "Spike_L452R": 0.00331858407079646, "Spike_N440K": 0.0, "Spike_N501Y": 0.7743362831858407, "Spike_P681R": 0.0, "Spike_Q493R": 0.0, "Spike_Q498R": 0.0, "Spike_R346K": 0.0, "Spike_S373P": 0.0, "Spike_S375F": 0.0, "Spike_S477N": 0.0011061946902654867, "Spike_T478K": 0.0, "Spike_V143del": 0.0022123893805309734, "Spike_V70del": 0.02765486725663717, "Spike_Y144del": 0.024336283185840708, "Spike_Y145H": 0.0, "Spike_Y505H": 0.0, "country": "Brazil", "date": "7 Mar 2021", "date_range": "7 Mar-14 Mar 2021", "submissions": 904.0}, {"Spike_D796Y": 0.0, "Spike_E484A": 0.0, "Spike_G339D": 0.0, "Spike_G446S": 0.0, "Spike_G496S": 0.0, "Spike_H69del": 0.028484231943031537, "Spike_K417N": 0.003051881993896236, "Spike_L452R": 0.0, "Spike_N440K": 0.0, "Spike_N501Y": 0.8484231943031536, "Spike_P681R": 0.0, "Spike_Q493R": 0.0, "Spike_Q498R": 0.0, "Spike_R346K": 0.0, "Spike_S373P": 0.0, "Spike_S375F": 0.0, "Spike_S477N": 0.0, "Spike_T478K": 0.0, "Spike_V143del": 0.003051881993896236, "Spike_V70del": 0.028484231943031537, "Spike_Y144del": 0.03255340793489318, "Spike_Y145H": 0.0, "Spike_Y505H": 0.0, "country": "Brazil", "date": "14 Mar 2021", "date_range": "14 Mar-21 Mar 2021", "submissions": 983.0}, {"Spike_D796Y": 0.0018796992481203006, "Spike_E484A": 0.0, "Spike_G339D": 0.0, "Spike_G446S": 0.0, "Spike_G496S": 0.0, "Spike_H69del": 0.02725563909774436, "Spike_K417N": 0.0, "Spike_L452R": 0.019736842105263157, "Spike_N440K": 0.0, "Spike_N501Y": 0.8759398496240601, "Spike_P681R": 0.0, "Spike_Q493R": 0.0, "Spike_Q498R": 0.0, "Spike_R346K": 0.0018796992481203006, "Spike_S373P": 0.0, "Spike_S375F": 0.0, "Spike_S477N": 0.0, "Spike_T478K": 0.0, "Spike_V143del": 0.0037593984962406013, "Spike_V70del": 0.02725563909774436, "Spike_Y144del": 0.02725563909774436, "Spike_Y145H": 0.0, "Spike_Y505H": 0.0, "country": "Brazil", "date": "21 Mar 2021", "date_range": "21 Mar-28 Mar 2021", "submissions": 1064.0}, {"Spike_D796Y": 0.0, "Spike_E484A": 0.0, "Spike_G339D": 0.0, "Spike_G446S": 0.0, "Spike_G496S": 0.0, "Spike_H69del": 0.041168658698539175, "Spike_K417N": 0.0, "Spike_L452R": 0.014608233731739707, "Spike_N440K": 0.0, "Spike_N501Y": 0.8851261620185923, "Spike_P681R": 0.0, "Spike_Q493R": 0.0, "Spike_Q498R": 0.0, "Spike_R346K": 0.0, "Spike_S373P": 0.0, "Spike_S375F": 0.0, "Spike_S477N": 0.0006640106241699867, "Spike_T478K": 0.0, "Spike_V143del": 0.00398406374501992, "Spike_V70del": 0.04249667994687915, "Spike_Y144del": 0.041168658698539175, "Spike_Y145H": 0.0, "Spike_Y505H": 0.0, "country": "Brazil", "date": "28 Mar 2021", "date_range": "28 Mar-4 Apr 2021", "submissions": 1506.0}, {"Spike_D796Y": 0.0, "Spike_E484A": 0.0, "Spike_G339D": 0.0, "Spike_G446S": 0.0, "Spike_G496S": 0.0, "Spike_H69del": 0.05584905660377359, "Spike_K417N": 0.0, "Spike_L452R": 0.012830188679245283, "Spike_N440K": 0.0, "Spike_N501Y": 0.9313207547169812, "Spike_P681R": 0.0, "Spike_Q493R": 0.0, "Spike_Q498R": 0.0, "Spike_R346K": 0.0, "Spike_S373P": 0.0007547169811320754, "Spike_S375F": 0.0, "Spike_S477N": 0.0, "Spike_T478K": 0.0, "Spike_V143del": 0.0060377358490566035, "Spike_V70del": 0.05660377358490566, "Spike_Y144del": 0.05660377358490566, "Spike_Y145H": 0.0, "Spike_Y505H": 0.0, "country": "Brazil", "date": "4 Apr 2021", "date_range": "4 Apr-11 Apr 2021", "submissions": 1325.0}, {"Spike_D796Y": 0.00046468401486988845, "Spike_E484A": 0.0, "Spike_G339D": 0.0, "Spike_G446S": 0.0, "Spike_G496S": 0.0, "Spike_H69del": 0.03949814126394052, "Spike_K417N": 0.0013940520446096654, "Spike_L452R": 0.007434944237918215, "Spike_N440K": 0.0, "Spike_N501Y": 0.929368029739777, "Spike_P681R": 0.00046468401486988845, "Spike_Q493R": 0.0, "Spike_Q498R": 0.0, "Spike_R346K": 0.00046468401486988845, "Spike_S373P": 0.00046468401486988845, "Spike_S375F": 0.0, "Spike_S477N": 0.0013940520446096654, "Spike_T478K": 0.0, "Spike_V143del": 0.0055762081784386614, "Spike_V70del": 0.039962825278810406, "Spike_Y144del": 0.04228624535315985, "Spike_Y145H": 0.0, "Spike_Y505H": 0.0, "country": "Brazil", "date": "11 Apr 2021", "date_range": "11 Apr-18 Apr 2021", "submissions": 2152.0}, {"Spike_D796Y": 0.0, "Spike_E484A": 0.0, "Spike_G339D": 0.0, "Spike_G446S": 0.0, "Spike_G496S": 0.0005973715651135006, "Spike_H69del": 0.03106332138590203, "Spike_K417N": 0.0, "Spike_L452R": 0.02031063321385902, "Spike_N440K": 0.0, "Spike_N501Y": 0.9241338112305855, "Spike_P681R": 0.0023894862604540022, "Spike_Q493R": 0.0011947431302270011, "Spike_Q498R": 0.0, "Spike_R346K": 0.0, "Spike_S373P": 0.0, "Spike_S375F": 0.0, "Spike_S477N": 0.0, "Spike_T478K": 0.0011947431302270011, "Spike_V143del": 0.0011947431302270011, "Spike_V70del": 0.03106332138590203, "Spike_Y144del": 0.03106332138590203, "Spike_Y145H": 0.0005973715651135006, "Spike_Y505H": 0.0, "country": "Brazil", "date": "18 Apr 2021", "date_range": "18 Apr-25 Apr 2021", "submissions": 1674.0}, {"Spike_D796Y": 0.0, "Spike_E484A": 0.0, "Spike_G339D": 0.0, "Spike_G446S": 0.0009799118079372856, "Spike_G496S": 0.0, "Spike_H69del": 0.03135717785399314, "Spike_K417N": 0.0, "Spike_L452R": 0.011268985791278784, "Spike_N440K": 0.0, "Spike_N501Y": 0.9647231749142577, "Spike_P681R": 0.0004899559039686428, "Spike_Q493R": 0.0, "Spike_Q498R": 0.0, "Spike_R346K": 0.0, "Spike_S373P": 0.0, "Spike_S375F": 0.0, "Spike_S477N": 0.0014698677119059284, "Spike_T478K": 0.0, "Spike_V143del": 0.004899559039686428, "Spike_V70del": 0.03135717785399314, "Spike_Y144del": 0.033806957373836356, "Spike_Y145H": 0.0, "Spike_Y505H": 0.0, "country": "Brazil", "date": "25 Apr 2021", "date_range": "25 Apr-2 May 2021", "submissions": 2041.0}, {"Spike_D796Y": 0.0, "Spike_E484A": 0.0, "Spike_G339D": 0.0011117287381878821, "Spike_G446S": 0.0, "Spike_G496S": 0.0, "Spike_H69del": 0.01556420233463035, "Spike_K417N": 0.0, "Spike_L452R": 0.007226236798221234, "Spike_N440K": 0.0, "Spike_N501Y": 0.962757087270706, "Spike_P681R": 0.0033351862145636463, "Spike_Q493R": 0.0005558643690939411, "Spike_Q498R": 0.0, "Spike_R346K": 0.0, "Spike_S373P": 0.0, "Spike_S375F": 0.0, "Spike_S477N": 0.0, "Spike_T478K": 0.0033351862145636463, "Spike_V143del": 0.0011117287381878821, "Spike_V70del": 0.01556420233463035, "Spike_Y144del": 0.022234574763757644, "Spike_Y145H": 0.0, "Spike_Y505H": 0.0, "country": "Brazil", "date": "2 May 2021", "date_range": "2 May-9 May 2021", "submissions": 1799.0}, {"Spike_D796Y": 0.0, "Spike_E484A": 0.0, "Spike_G339D": 0.0, "Spike_G446S": 0.0, "Spike_G496S": 0.0, "Spike_H69del": 0.022653721682847898, "Spike_K417N": 0.0, "Spike_L452R": 0.007119741100323625, "Spike_N440K": 0.0, "Spike_N501Y": 0.943042071197411, "Spike_P681R": 0.0006472491909385113, "Spike_Q493R": 0.0, "Spike_Q498R": 0.0, "Spike_R346K": 0.0, "Spike_S373P": 0.0, "Spike_S375F": 0.0, "Spike_S477N": 0.0, "Spike_T478K": 0.0, "Spike_V143del": 0.003236245954692557, "Spike_V70del": 0.022653721682847898, "Spike_Y144del": 0.026537216828478965, "Spike_Y145H": 0.0, "Spike_Y505H": 0.0, "country": "Brazil", "date": "9 May 2021", "date_range": "9 May-16 May 2021", "submissions": 1545.0}, {"Spike_D796Y": 0.0005733944954128441, "Spike_E484A": 0.0, "Spike_G339D": 0.0011467889908256881, "Spike_G446S": 0.0, "Spike_G496S": 0.0, "Spike_H69del": 0.0194954128440367, "Spike_K417N": 0.0, "Spike_L452R": 0.012041284403669725, "Spike_N440K": 0.0, "Spike_N501Y": 0.9283256880733946, "Spike_P681R": 0.006307339449541285, "Spike_Q493R": 0.0, "Spike_Q498R": 0.0, "Spike_R346K": 0.0, "Spike_S373P": 0.0, "Spike_S375F": 0.0, "Spike_S477N": 0.0005733944954128441, "Spike_T478K": 0.0040137614678899085, "Spike_V143del": 0.005160550458715597, "Spike_V70del": 0.0194954128440367, "Spike_Y144del": 0.02236238532110092, "Spike_Y145H": 0.0005733944954128441, "Spike_Y505H": 0.0, "country": "Brazil", "date": "16 May 2021", "date_range": "16 May-23 May 2021", "submissions": 1744.0}, {"Spike_D796Y": 0.00047596382674916705, "Spike_E484A": 0.0, "Spike_G339D": 0.0, "Spike_G446S": 0.0, "Spike_G496S": 0.0, "Spike_H69del": 0.029033793431699192, "Spike_K417N": 0.0, "Spike_L452R": 0.01285102332222751, "Spike_N440K": 0.0, "Spike_N501Y": 0.9076630176106616, "Spike_P681R": 0.0014278914802475012, "Spike_Q493R": 0.0, "Spike_Q498R": 0.0, "Spike_R346K": 0.0, "Spike_S373P": 0.0, "Spike_S375F": 0.0, "Spike_S477N": 0.0, "Spike_T478K": 0.0014278914802475012, "Spike_V143del": 0.006187529747739172, "Spike_V70del": 0.029509757258448358, "Spike_Y144del": 0.03664921465968586, "Spike_Y145H": 0.0, "Spike_Y505H": 0.00047596382674916705, "country": "Brazil", "date": "23 May 2021", "date_range": "23 May-30 May 2021", "submissions": 2101.0}, {"Spike_D796Y": 0.0009372071227741331, "Spike_E484A": 0.0, "Spike_G339D": 0.00046860356138706655, "Spike_G446S": 0.0, "Spike_G496S": 0.0, "Spike_H69del": 0.04076850984067479, "Spike_K417N": 0.0, "Spike_L452R": 0.0037488284910965324, "Spike_N440K": 0.00046860356138706655, "Spike_N501Y": 0.9498594189315839, "Spike_P681R": 0.0032802249297094657, "Spike_Q493R": 0.0, "Spike_Q498R": 0.0, "Spike_R346K": 0.0, "Spike_S373P": 0.00046860356138706655, "Spike_S375F": 0.0, "Spike_S477N": 0.0, "Spike_T478K": 0.00046860356138706655, "Spike_V143del": 0.005623242736644799, "Spike_V70del": 0.04076850984067479, "Spike_Y144del": 0.04779756326148079, "Spike_Y145H": 0.00046860356138706655, "Spike_Y505H": 0.0, "country": "Brazil", "date": "30 May 2021", "date_range": "30 May-6 Jun 2021", "submissions": 2134.0}, {"Spike_D796Y": 0.005633802816901409, "Spike_E484A": 0.0, "Spike_G339D": 0.0, "Spike_G446S": 0.0, "Spike_G496S": 0.0, "Spike_H69del": 0.0358148893360161, "Spike_K417N": 0.0, "Spike_L452R": 0.012474849094567404, "Spike_N440K": 0.0, "Spike_N501Y": 0.9231388329979879, "Spike_P681R": 0.004024144869215292, "Spike_Q493R": 0.00040241448692152917, "Spike_Q498R": 0.0, "Spike_R346K": 0.0012072434607645875, "Spike_S373P": 0.00040241448692152917, "Spike_S375F": 0.0, "Spike_S477N": 0.0, "Spike_T478K": 0.0016096579476861167, "Spike_V143del": 0.002012072434607646, "Spike_V70del": 0.0358148893360161, "Spike_Y144del": 0.03943661971830986, "Spike_Y145H": 0.0, "Spike_Y505H": 0.0, "country": "Brazil", "date": "6 Jun 2021", "date_range": "6 Jun-13 Jun 2021", "submissions": 2485.0}, {"Spike_D796Y": 0.002112676056338028, "Spike_E484A": 0.0, "Spike_G339D": 0.0007042253521126761, "Spike_G446S": 0.0, "Spike_G496S": 0.0, "Spike_H69del": 0.03169014084507042, "Spike_K417N": 0.0, "Spike_L452R": 0.007746478873239437, "Spike_N440K": 0.0, "Spike_N501Y": 0.9144366197183098, "Spike_P681R": 0.006338028169014085, "Spike_Q493R": 0.0, "Spike_Q498R": 0.0, "Spike_R346K": 0.0, "Spike_S373P": 0.0, "Spike_S375F": 0.0, "Spike_S477N": 0.0, "Spike_T478K": 0.0031690140845070424, "Spike_V143del": 0.0031690140845070424, "Spike_V70del": 0.03169014084507042, "Spike_Y144del": 0.03838028169014084, "Spike_Y145H": 0.0, "Spike_Y505H": 0.00035211267605633805, "country": "Brazil", "date": "13 Jun 2021", "date_range": "13 Jun-20 Jun 2021", "submissions": 2840.0}, {"Spike_D796Y": 0.0, "Spike_E484A": 0.0, "Spike_G339D": 0.0, "Spike_G446S": 0.0, "Spike_G496S": 0.0, "Spike_H69del": 0.024752475247524754, "Spike_K417N": 0.0, "Spike_L452R": 0.009900990099009901, "Spike_N440K": 0.0, "Spike_N501Y": 0.9518451845184518, "Spike_P681R": 0.008550855085508551, "Spike_Q493R": 0.0, "Spike_Q498R": 0.0, "Spike_R346K": 0.0009000900090009, "Spike_S373P": 0.0, "Spike_S375F": 0.0, "Spike_S477N": 0.0, "Spike_T478K": 0.0058505850585058505, "Spike_V143del": 0.0027002700270027003, "Spike_V70del": 0.024752475247524754, "Spike_Y144del": 0.0288028802880288, "Spike_Y145H": 0.00045004500450045, "Spike_Y505H": 0.0, "country": "Brazil", "date": "20 Jun 2021", "date_range": "20 Jun-27 Jun 2021", "submissions": 2222.0}, {"Spike_D796Y": 0.0, "Spike_E484A": 0.0, "Spike_G339D": 0.0, "Spike_G446S": 0.0, "Spike_G496S": 0.0, "Spike_H69del": 0.014636246233318984, "Spike_K417N": 0.0, "Spike_L452R": 0.018941024537236333, "Spike_N440K": 0.0, "Spike_N501Y": 0.9509255273353422, "Spike_P681R": 0.02238484718037021, "Spike_Q493R": 0.0, "Spike_Q498R": 0.0, "Spike_R346K": 0.0012914334911752045, "Spike_S373P": 0.0, "Spike_S375F": 0.0, "Spike_S477N": 0.00043047783039173483, "Spike_T478K": 0.015066724063710719, "Spike_V143del": 0.003013344812742144, "Spike_V70del": 0.014636246233318984, "Spike_Y144del": 0.019801980198019802, "Spike_Y145H": 0.0, "Spike_Y505H": 0.00043047783039173483, "country": "Brazil", "date": "27 Jun 2021", "date_range": "27 Jun-4 Jul 2021", "submissions": 2323.0}, {"Spike_D796Y": 0.0003117206982543641, "Spike_E484A": 0.0, "Spike_G339D": 0.0, "Spike_G446S": 0.0, "Spike_G496S": 0.0, "Spike_H69del": 0.016521197007481298, "Spike_K417N": 0.0, "Spike_L452R": 0.034912718204488775, "Spike_N440K": 0.0003117206982543641, "Spike_N501Y": 0.9267456359102244, "Spike_P681R": 0.042082294264339154, "Spike_Q493R": 0.0, "Spike_Q498R": 0.0, "Spike_R346K": 0.0006234413965087282, "Spike_S373P": 0.0006234413965087282, "Spike_S375F": 0.0, "Spike_S477N": 0.0, "Spike_T478K": 0.033354114713216955, "Spike_V143del": 0.0021820448877805485, "Spike_V70del": 0.016521197007481298, "Spike_Y144del": 0.025561097256857856, "Spike_Y145H": 0.0, "Spike_Y505H": 0.0003117206982543641, "country": "Brazil", "date": "4 Jul 2021", "date_range": "4 Jul-11 Jul 2021", "submissions": 3208.0}, {"Spike_D796Y": 0.0004068348250610252, "Spike_E484A": 0.0, "Spike_G339D": 0.0, "Spike_G446S": 0.0, "Spike_G496S": 0.0004068348250610252, "Spike_H69del": 0.006102522375915379, "Spike_K417N": 0.0008136696501220504, "Spike_L452R": 0.07485760781122865, "Spike_N440K": 0.0, "Spike_N501Y": 0.871847030105777, "Spike_P681R": 0.0854353132628153, "Spike_Q493R": 0.0, "Spike_Q498R": 0.0, "Spike_R346K": 0.0008136696501220504, "Spike_S373P": 0.0, "Spike_S375F": 0.0, "Spike_S477N": 0.0, "Spike_T478K": 0.07526444263628966, "Spike_V143del": 0.0016273393002441008, "Spike_V70del": 0.006102522375915379, "Spike_Y144del": 0.008950366151342554, "Spike_Y145H": 0.0, "Spike_Y505H": 0.0004068348250610252, "country": "Brazil", "date": "11 Jul 2021", "date_range": "11 Jul-18 Jul 2021", "submissions": 2458.0}, {"Spike_D796Y": 0.00035174111853675694, "Spike_E484A": 0.0, "Spike_G339D": 0.0, "Spike_G446S": 0.00035174111853675694, "Spike_G496S": 0.0, "Spike_H69del": 0.008793527963418923, "Spike_K417N": 0.0007034822370735139, "Spike_L452R": 0.09250791417516707, "Spike_N440K": 0.0, "Spike_N501Y": 0.8445304256067534, "Spike_P681R": 0.11185367569468871, "Spike_Q493R": 0.0, "Spike_Q498R": 0.0, "Spike_R346K": 0.0014069644741470278, "Spike_S373P": 0.00035174111853675694, "Spike_S375F": 0.0, "Spike_S477N": 0.0, "Spike_T478K": 0.09250791417516707, "Spike_V143del": 0.002110446711220542, "Spike_V70del": 0.008793527963418923, "Spike_Y144del": 0.017587055926837847, "Spike_Y145H": 0.0, "Spike_Y505H": 0.0, "country": "Brazil", "date": "18 Jul 2021", "date_range": "18 Jul-25 Jul 2021", "submissions": 2843.0}, {"Spike_D796Y": 0.0, "Spike_E484A": 0.0, "Spike_G339D": 0.0, "Spike_G446S": 0.0, "Spike_G496S": 0.0, "Spike_H69del": 0.0079155672823219, "Spike_K417N": 0.0, "Spike_L452R": 0.1236336223143611, "Spike_N440K": 0.0, "Spike_N501Y": 0.8073878627968337, "Spike_P681R": 0.13494157557482095, "Spike_Q493R": 0.0, "Spike_Q498R": 0.0, "Spike_R346K": 0.0003769317753486619, "Spike_S373P": 0.0, "Spike_S375F": 0.0, "Spike_S477N": 0.0, "Spike_T478K": 0.12250282698831512, "Spike_V143del": 0.0015077271013946476, "Spike_V70del": 0.0079155672823219, "Spike_Y144del": 0.01394647568790049, "Spike_Y145H": 0.0, "Spike_Y505H": 0.0, "country": "Brazil", "date": "25 Jul 2021", "date_range": "25 Jul-1 Aug 2021", "submissions": 2653.0}, {"Spike_D796Y": 0.0, "Spike_E484A": 0.0, "Spike_G339D": 0.0, "Spike_G446S": 0.0, "Spike_G496S": 0.0, "Spike_H69del": 0.007563025210084034, "Spike_K417N": 0.0, "Spike_L452R": 0.22478991596638656, "Spike_N440K": 0.0, "Spike_N501Y": 0.6949579831932773, "Spike_P681R": 0.24705882352941178, "Spike_Q493R": 0.0, "Spike_Q498R": 0.0, "Spike_R346K": 0.0016806722689075631, "Spike_S373P": 0.0, "Spike_S375F": 0.0, "Spike_S477N": 0.0, "Spike_T478K": 0.22394957983193278, "Spike_V143del": 0.0012605042016806723, "Spike_V70del": 0.007563025210084034, "Spike_Y144del": 0.012184873949579832, "Spike_Y145H": 0.0008403361344537816, "Spike_Y505H": 0.0, "country": "Brazil", "date": "1 Aug 2021", "date_range": "1 Aug-8 Aug 2021", "submissions": 2380.0}, {"Spike_D796Y": 0.00033852403520649965, "Spike_E484A": 0.0, "Spike_G339D": 0.0, "Spike_G446S": 0.00033852403520649965, "Spike_G496S": 0.0, "Spike_H69del": 0.002369668246445498, "Spike_K417N": 0.0, "Spike_L452R": 0.3111035883547732, "Spike_N440K": 0.0, "Spike_N501Y": 0.6100203114421124, "Spike_P681R": 0.34326337169939064, "Spike_Q493R": 0.0, "Spike_Q498R": 0.0, "Spike_R346K": 0.002031144211238998, "Spike_S373P": 0.002369668246445498, "Spike_S375F": 0.0, "Spike_S477N": 0.0, "Spike_T478K": 0.3104265402843602, "Spike_V143del": 0.0050778605280974946, "Spike_V70del": 0.002369668246445498, "Spike_Y144del": 0.011848341232227487, "Spike_Y145H": 0.0, "Spike_Y505H": 0.0, "country": "Brazil", "date": "8 Aug 2021", "date_range": "8 Aug-15 Aug 2021", "submissions": 2954.0}, {"Spike_D796Y": 0.0, "Spike_E484A": 0.0, "Spike_G339D": 0.0, "Spike_G446S": 0.00041050903119868636, "Spike_G496S": 0.0, "Spike_H69del": 0.003694581280788177, "Spike_K417N": 0.00041050903119868636, "Spike_L452R": 0.5923645320197044, "Spike_N440K": 0.0, "Spike_N501Y": 0.34195402298850575, "Spike_P681R": 0.6338259441707718, "Spike_Q493R": 0.0, "Spike_Q498R": 0.0, "Spike_R346K": 0.002052545155993432, "Spike_S373P": 0.0, "Spike_S375F": 0.0, "Spike_S477N": 0.0, "Spike_T478K": 0.5960591133004927, "Spike_V143del": 0.0012315270935960591, "Spike_V70del": 0.003694581280788177, "Spike_Y144del": 0.006568144499178982, "Spike_Y145H": 0.0, "Spike_Y505H": 0.0, "country": "Brazil", "date": "15 Aug 2021", "date_range": "15 Aug-22 Aug 2021", "submissions": 2436.0}, {"Spike_D796Y": 0.0, "Spike_E484A": 0.0, "Spike_G339D": 0.0, "Spike_G446S": 0.0, "Spike_G496S": 0.0, "Spike_H69del": 0.002061855670103093, "Spike_K417N": 0.0, "Spike_L452R": 0.6510309278350516, "Spike_N440K": 0.0, "Spike_N501Y": 0.29536082474226805, "Spike_P681R": 0.6747422680412372, "Spike_Q493R": 0.0, "Spike_Q498R": 0.0, "Spike_R346K": 0.0015463917525773195, "Spike_S373P": 0.0, "Spike_S375F": 0.0, "Spike_S477N": 0.0, "Spike_T478K": 0.6530927835051547, "Spike_V143del": 0.0005154639175257732, "Spike_V70del": 0.002061855670103093, "Spike_Y144del": 0.00979381443298969, "Spike_Y145H": 0.0010309278350515464, "Spike_Y505H": 0.0, "country": "Brazil", "date": "22 Aug 2021", "date_range": "22 Aug-29 Aug 2021", "submissions": 1940.0}, {"Spike_D796Y": 0.0, "Spike_E484A": 0.0, "Spike_G339D": 0.0, "Spike_G446S": 0.0, "Spike_G496S": 0.0, "Spike_H69del": 0.0020652622883106154, "Spike_K417N": 0.0, "Spike_L452R": 0.7257331681123502, "Spike_N440K": 0.0, "Spike_N501Y": 0.23543990086741015, "Spike_P681R": 0.7529946303180504, "Spike_Q493R": 0.0, "Spike_Q498R": 0.0, "Spike_R346K": 0.0, "Spike_S373P": 0.0, "Spike_S375F": 0.0, "Spike_S477N": 0.0, "Spike_T478K": 0.7277984304006608, "Spike_V143del": 0.0, "Spike_V70del": 0.0020652622883106154, "Spike_Y144del": 0.004130524576621231, "Spike_Y145H": 0.0004130524576621231, "Spike_Y505H": 0.0004130524576621231, "country": "Brazil", "date": "29 Aug 2021", "date_range": "29 Aug-5 Sep 2021", "submissions": 2421.0}, {"Spike_D796Y": 0.000608457560085184, "Spike_E484A": 0.0, "Spike_G339D": 0.0, "Spike_G446S": 0.0, "Spike_G496S": 0.0, "Spike_H69del": 0.001216915120170368, "Spike_K417N": 0.0, "Spike_L452R": 0.8484940675387892, "Spike_N440K": 0.000304228780042592, "Spike_N501Y": 0.11317310617584424, "Spike_P681R": 0.8719196836020687, "Spike_Q493R": 0.0, "Spike_Q498R": 0.0, "Spike_R346K": 0.0009126863401277761, "Spike_S373P": 0.0, "Spike_S375F": 0.0, "Spike_S477N": 0.0, "Spike_T478K": 0.8503194402190447, "Spike_V143del": 0.000304228780042592, "Spike_V70del": 0.001216915120170368, "Spike_Y144del": 0.004867660480681472, "Spike_Y145H": 0.000608457560085184, "Spike_Y505H": 0.0, "country": "Brazil", "date": "5 Sep 2021", "date_range": "5 Sep-12 Sep 2021", "submissions": 3287.0}, {"Spike_D796Y": 0.0, "Spike_E484A": 0.0, "Spike_G339D": 0.00030703101013202335, "Spike_G446S": 0.00030703101013202335, "Spike_G496S": 0.0, "Spike_H69del": 0.003070310101320233, "Spike_K417N": 0.0, "Spike_L452R": 0.8513969910961007, "Spike_N440K": 0.0006140620202640467, "Spike_N501Y": 0.08873196192815475, "Spike_P681R": 0.8925391464537918, "Spike_Q493R": 0.0, "Spike_Q498R": 0.0, "Spike_R346K": 0.00030703101013202335, "Spike_S373P": 0.0, "Spike_S375F": 0.0, "Spike_S477N": 0.0, "Spike_T478K": 0.8504758980657047, "Spike_V143del": 0.0, "Spike_V70del": 0.003070310101320233, "Spike_Y144del": 0.0021492170709241634, "Spike_Y145H": 0.0, "Spike_Y505H": 0.0, "country": "Brazil", "date": "12 Sep 2021", "date_range": "12 Sep-19 Sep 2021", "submissions": 3257.0}, {"Spike_D796Y": 0.0, "Spike_E484A": 0.00035523978685612787, "Spike_G339D": 0.0, "Spike_G446S": 0.00035523978685612787, "Spike_G496S": 0.0, "Spike_H69del": 0.00497335701598579, "Spike_K417N": 0.00035523978685612787, "Spike_L452R": 0.8142095914742451, "Spike_N440K": 0.00035523978685612787, "Spike_N501Y": 0.09698046181172292, "Spike_P681R": 0.855772646536412, "Spike_Q493R": 0.0, "Spike_Q498R": 0.0, "Spike_R346K": 0.0, "Spike_S373P": 0.0, "Spike_S375F": 0.0, "Spike_S477N": 0.0, "Spike_T478K": 0.7925399644760213, "Spike_V143del": 0.002486678507992895, "Spike_V70del": 0.00497335701598579, "Spike_Y144del": 0.003552397868561279, "Spike_Y145H": 0.0, "Spike_Y505H": 0.0, "country": "Brazil", "date": "19 Sep 2021", "date_range": "19 Sep-26 Sep 2021", "submissions": 2815.0}, {"Spike_D796Y": 0.0009857072449482504, "Spike_E484A": 0.0, "Spike_G339D": 0.0, "Spike_G446S": 0.0, "Spike_G496S": 0.0, "Spike_H69del": 0.003942828979793002, "Spike_K417N": 0.0004928536224741252, "Spike_L452R": 0.9048792508624939, "Spike_N440K": 0.0009857072449482504, "Spike_N501Y": 0.0704780680137999, "Spike_P681R": 0.9265648102513554, "Spike_Q493R": 0.0, "Spike_Q498R": 0.0, "Spike_R346K": 0.0, "Spike_S373P": 0.0, "Spike_S375F": 0.0, "Spike_S477N": 0.0, "Spike_T478K": 0.8905864958107442, "Spike_V143del": 0.0014785608674223755, "Spike_V70del": 0.003942828979793002, "Spike_Y144del": 0.0014785608674223755, "Spike_Y145H": 0.0, "Spike_Y505H": 0.0, "country": "Brazil", "date": "26 Sep 2021", "date_range": "26 Sep-3 Oct 2021", "submissions": 2029.0}, {"Spike_D796Y": 0.0006832934745473181, "Spike_E484A": 0.00034164673727365904, "Spike_G339D": 0.0, "Spike_G446S": 0.0, "Spike_G496S": 0.0, "Spike_H69del": 0.0010249402118209772, "Spike_K417N": 0.00034164673727365904, "Spike_L452R": 0.9313290058079945, "Spike_N440K": 0.0010249402118209772, "Spike_N501Y": 0.039631021523744446, "Spike_P681R": 0.9542193372053297, "Spike_Q493R": 0.0, "Spike_Q498R": 0.0, "Spike_R346K": 0.00034164673727365904, "Spike_S373P": 0.0, "Spike_S375F": 0.0, "Spike_S477N": 0.0, "Spike_T478K": 0.9227878373761531, "Spike_V143del": 0.0, "Spike_V70del": 0.0010249402118209772, "Spike_Y144del": 0.0030748206354629312, "Spike_Y145H": 0.0, "Spike_Y505H": 0.0, "country": "Brazil", "date": "3 Oct 2021", "date_range": "3 Oct-10 Oct 2021", "submissions": 2927.0}, {"Spike_D796Y": 0.0, "Spike_E484A": 0.0006759040216289286, "Spike_G339D": 0.0, "Spike_G446S": 0.0, "Spike_G496S": 0.0, "Spike_H69del": 0.0003379520108144643, "Spike_K417N": 0.0, "Spike_L452R": 0.9205812774586009, "Spike_N440K": 0.0013518080432578573, "Spike_N501Y": 0.021966880702940183, "Spike_P681R": 0.9705981750591416, "Spike_Q493R": 0.0, "Spike_Q498R": 0.0, "Spike_R346K": 0.0, "Spike_S373P": 0.0, "Spike_S375F": 0.0, "Spike_S477N": 0.0, "Spike_T478K": 0.9263264616424468, "Spike_V143del": 0.0, "Spike_V70del": 0.0003379520108144643, "Spike_Y144del": 0.0016897600540723217, "Spike_Y145H": 0.0, "Spike_Y505H": 0.0, "country": "Brazil", "date": "10 Oct 2021", "date_range": "10 Oct-17 Oct 2021", "submissions": 2959.0}, {"Spike_D796Y": 0.0, "Spike_E484A": 0.0, "Spike_G339D": 0.0, "Spike_G446S": 0.0, "Spike_G496S": 0.0, "Spike_H69del": 0.0009250693802035153, "Spike_K417N": 0.0, "Spike_L452R": 0.9375578168362627, "Spike_N440K": 0.0009250693802035153, "Spike_N501Y": 0.0074005550416281225, "Spike_P681R": 0.9791859389454209, "Spike_Q493R": 0.0, "Spike_Q498R": 0.00046253469010175765, "Spike_R346K": 0.0, "Spike_S373P": 0.0, "Spike_S375F": 0.0, "Spike_S477N": 0.0, "Spike_T478K": 0.9444958371877891, "Spike_V143del": 0.0, "Spike_V70del": 0.0009250693802035153, "Spike_Y144del": 0.002312673450508788, "Spike_Y145H": 0.0, "Spike_Y505H": 0.0, "country": "Brazil", "date": "17 Oct 2021", "date_range": "17 Oct-24 Oct 2021", "submissions": 2162.0}, {"Spike_D796Y": 0.0004885197850512946, "Spike_E484A": 0.0, "Spike_G339D": 0.0, "Spike_G446S": 0.0, "Spike_G496S": 0.0, "Spike_H69del": 0.0, "Spike_K417N": 0.0, "Spike_L452R": 0.920371275036639, "Spike_N440K": 0.0019540791402051783, "Spike_N501Y": 0.01074743527112848, "Spike_P681R": 0.9829018075232047, "Spike_Q493R": 0.0, "Spike_Q498R": 0.0, "Spike_R346K": 0.0, "Spike_S373P": 0.0004885197850512946, "Spike_S375F": 0.0, "Spike_S477N": 0.0, "Spike_T478K": 0.9325842696629213, "Spike_V143del": 0.0004885197850512946, "Spike_V70del": 0.0, "Spike_Y144del": 0.0014655593551538837, "Spike_Y145H": 0.0, "Spike_Y505H": 0.0, "country": "Brazil", "date": "24 Oct 2021", "date_range": "24 Oct-31 Oct 2021", "submissions": 2047.0}, {"Spike_D796Y": 0.0, "Spike_E484A": 0.0, "Spike_G339D": 0.0, "Spike_G446S": 0.0, "Spike_G496S": 0.0, "Spike_H69del": 0.0005688282138794084, "Spike_K417N": 0.0, "Spike_L452R": 0.906712172923777, "Spike_N440K": 0.0011376564277588168, "Spike_N501Y": 0.00739476678043231, "Spike_P681R": 0.9869169510807736, "Spike_Q493R": 0.0, "Spike_Q498R": 0.0, "Spike_R346K": 0.0, "Spike_S373P": 0.0, "Spike_S375F": 0.0, "Spike_S477N": 0.0, "Spike_T478K": 0.9124004550625711, "Spike_V143del": 0.0, "Spike_V70del": 0.0005688282138794084, "Spike_Y144del": 0.0, "Spike_Y145H": 0.0, "Spike_Y505H": 0.0, "country": "Brazil", "date": "31 Oct 2021", "date_range": "31 Oct-7 Nov 2021", "submissions": 1758.0}, {"Spike_D796Y": 0.0, "Spike_E484A": 0.0004182350480970305, "Spike_G339D": 0.0, "Spike_G446S": 0.0004182350480970305, "Spike_G496S": 0.0, "Spike_H69del": 0.000836470096194061, "Spike_K417N": 0.0, "Spike_L452R": 0.9104976997072355, "Spike_N440K": 0.0012547051442910915, "Spike_N501Y": 0.004600585529067336, "Spike_P681R": 0.9891258887494772, "Spike_Q493R": 0.0, "Spike_Q498R": 0.0, "Spike_R346K": 0.0, "Spike_S373P": 0.0, "Spike_S375F": 0.0, "Spike_S477N": 0.0004182350480970305, "Spike_T478K": 0.9134253450439147, "Spike_V143del": 0.0, "Spike_V70del": 0.000836470096194061, "Spike_Y144del": 0.000836470096194061, "Spike_Y145H": 0.0004182350480970305, "Spike_Y505H": 0.0, "country": "Brazil", "date": "7 Nov 2021", "date_range": "7 Nov-14 Nov 2021", "submissions": 2391.0}, {"Spike_D796Y": 0.0, "Spike_E484A": 0.0, "Spike_G339D": 0.0, "Spike_G446S": 0.0, "Spike_G496S": 0.0, "Spike_H69del": 0.0012325390304026294, "Spike_K417N": 0.0, "Spike_L452R": 0.9190632703368941, "Spike_N440K": 0.002875924404272802, "Spike_N501Y": 0.002875924404272802, "Spike_P681R": 0.9909613804437141, "Spike_Q493R": 0.0, "Spike_Q498R": 0.0, "Spike_R346K": 0.0, "Spike_S373P": 0.0, "Spike_S375F": 0.0, "Spike_S477N": 0.0, "Spike_T478K": 0.924404272801972, "Spike_V143del": 0.0, "Spike_V70del": 0.0012325390304026294, "Spike_Y144del": 0.0012325390304026294, "Spike_Y145H": 0.0004108463434675431, "Spike_Y505H": 0.0, "country": "Brazil", "date": "14 Nov 2021", "date_range": "14 Nov-21 Nov 2021", "submissions": 2434.0}, {"Spike_D796Y": 0.0010198878123406426, "Spike_E484A": 0.0010198878123406426, "Spike_G339D": 0.0, "Spike_G446S": 0.0, "Spike_G496S": 0.0, "Spike_H69del": 0.0005099439061703213, "Spike_K417N": 0.0, "Spike_L452R": 0.9627740948495666, "Spike_N440K": 0.0071392146863844975, "Spike_N501Y": 0.0030596634370219276, "Spike_P681R": 0.9898011218765935, "Spike_Q493R": 0.0, "Spike_Q498R": 0.0010198878123406426, "Spike_R346K": 0.0, "Spike_S373P": 0.0, "Spike_S375F": 0.0, "Spike_S477N": 0.0, "Spike_T478K": 0.9637939826619072, "Spike_V143del": 0.0005099439061703213, "Spike_V70del": 0.0005099439061703213, "Spike_Y144del": 0.00407955124936257, "Spike_Y145H": 0.0, "Spike_Y505H": 0.0, "country": "Brazil", "date": "21 Nov 2021", "date_range": "21 Nov-28 Nov 2021", "submissions": 1961.0}, {"Spike_D796Y": 0.0029779630732578916, "Spike_E484A": 0.0029779630732578916, "Spike_G339D": 0.0029779630732578916, "Spike_G446S": 0.00357355568790947, "Spike_G496S": 0.0029779630732578916, "Spike_H69del": 0.004169148302561048, "Spike_K417N": 0.0029779630732578916, "Spike_L452R": 0.9523525908278737, "Spike_N440K": 0.008933889219773675, "Spike_N501Y": 0.004169148302561048, "Spike_P681R": 0.9904705181655747, "Spike_Q493R": 0.0029779630732578916, "Spike_Q498R": 0.0023823704586063135, "Spike_R346K": 0.0, "Spike_S373P": 0.00357355568790947, "Spike_S375F": 0.0029779630732578916, "Spike_S477N": 0.0029779630732578916, "Spike_T478K": 0.9630732578916021, "Spike_V143del": 0.00357355568790947, "Spike_V70del": 0.004169148302561048, "Spike_Y144del": 0.006551518761167362, "Spike_Y145H": 0.0, "Spike_Y505H": 0.0023823704586063135, "country": "Brazil", "date": "28 Nov 2021", "date_range": "28 Nov-5 Dec 2021", "submissions": 1679.0}, {"Spike_D796Y": 0.004626569729015202, "Spike_E484A": 0.004626569729015202, "Spike_G339D": 0.0039656311962987445, "Spike_G446S": 0.0039656311962987445, "Spike_G496S": 0.0039656311962987445, "Spike_H69del": 0.006609385327164574, "Spike_K417N": 0.003304692663582287, "Spike_L452R": 0.9319233311302049, "Spike_N440K": 0.007270323859881031, "Spike_N501Y": 0.005287508261731659, "Spike_P681R": 0.9907468605419696, "Spike_Q493R": 0.0039656311962987445, "Spike_Q498R": 0.0039656311962987445, "Spike_R346K": 0.0013218770654329147, "Spike_S373P": 0.0026437541308658294, "Spike_S375F": 0.0026437541308658294, "Spike_S477N": 0.0039656311962987445, "Spike_T478K": 0.9451421017845341, "Spike_V143del": 0.005948446794448116, "Spike_V70del": 0.006609385327164574, "Spike_Y144del": 0.008592200925313946, "Spike_Y145H": 0.0026437541308658294, "Spike_Y505H": 0.0039656311962987445, "country": "Brazil", "date": "5 Dec 2021", "date_range": "5 Dec-12 Dec 2021", "submissions": 1513.0}, {"Spike_D796Y": 0.06379707916986933, "Spike_E484A": 0.0568793235972329, "Spike_G339D": 0.0568793235972329, "Spike_G446S": 0.05073020753266718, "Spike_G496S": 0.056110684089162186, "Spike_H69del": 0.0730207532667179, "Spike_K417N": 0.04611837048424289, "Spike_L452R": 0.8631821675634127, "Spike_N440K": 0.06072252113758647, "Spike_N501Y": 0.0568793235972329, "Spike_P681R": 0.9277478862413528, "Spike_Q493R": 0.056110684089162186, "Spike_Q498R": 0.05534204458109147, "Spike_R346K": 0.013835511145272867, "Spike_S373P": 0.05226748654880861, "Spike_S375F": 0.05226748654880861, "Spike_S477N": 0.056110684089162186, "Spike_T478K": 0.9185242121445042, "Spike_V143del": 0.06610299769408147, "Spike_V70del": 0.0730207532667179, "Spike_Y144del": 0.0668716372021522, "Spike_Y145H": 0.0023059185242121443, "Spike_Y505H": 0.05534204458109147, "country": "Brazil", "date": "12 Dec 2021", "date_range": "12 Dec-19 Dec 2021", "submissions": 1301.0}, {"Spike_D796Y": 0.21355397951142632, "Spike_E484A": 0.17572892040977148, "Spike_G339D": 0.1938534278959811, "Spike_G446S": 0.16154452324665092, "Spike_G496S": 0.17494089834515367, "Spike_H69del": 0.21828211189913319, "Spike_K417N": 0.14814814814814814, "Spike_L452R": 0.7320724980299448, "Spike_N440K": 0.14657210401891252, "Spike_N501Y": 0.1702127659574468, "Spike_P681R": 0.7722616233254531, "Spike_Q493R": 0.17415287628053586, "Spike_Q498R": 0.169424743892829, "Spike_R346K": 0.02442868400315209, "Spike_S373P": 0.15839243498817968, "Spike_S375F": 0.15839243498817968, "Spike_S477N": 0.17494089834515367, "Spike_T478K": 0.9109535066981875, "Spike_V143del": 0.2111899133175729, "Spike_V70del": 0.21828211189913319, "Spike_Y144del": 0.21434200157604413, "Spike_Y145H": 0.0, "Spike_Y505H": 0.16390858944050432, "country": "Brazil", "date": "19 Dec 2021", "date_range": "19 Dec-26 Dec 2021", "submissions": 1269.0}, {"Spike_D796Y": 0.5, "Spike_E484A": 0.3611111111111111, "Spike_G339D": 0.44166666666666665, "Spike_G446S": 0.3333333333333333, "Spike_G496S": 0.35648148148148145, "Spike_H69del": 0.49166666666666664, "Spike_K417N": 0.2962962962962963, "Spike_L452R": 0.43425925925925923, "Spike_N440K": 0.3, "Spike_N501Y": 0.3453703703703704, "Spike_P681R": 0.4842592592592593, "Spike_Q493R": 0.3592592592592593, "Spike_Q498R": 0.34074074074074073, "Spike_R346K": 0.04814814814814815, "Spike_S373P": 0.3351851851851852, "Spike_S375F": 0.33796296296296297, "Spike_S477N": 0.3611111111111111, "Spike_T478K": 0.8046296296296296, "Spike_V143del": 0.49074074074074076, "Spike_V70del": 0.49166666666666664, "Spike_Y144del": 0.49166666666666664, "Spike_Y145H": 0.000925925925925926, "Spike_Y505H": 0.3351851851851852, "country": "Brazil", "date": "26 Dec 2021", "date_range": "26 Dec-2 Jan 2022", "submissions": 1080.0}, {"Spike_D796Y": 0.8668861712135466, "Spike_E484A": 0.5860771401693321, "Spike_G339D": 0.7699905926622765, "Spike_G446S": 0.5451552210724365, "Spike_G496S": 0.5827845719661335, "Spike_H69del": 0.8607714016933208, "Spike_K417N": 0.5653809971777987, "Spike_L452R": 0.10677328316086547, "Spike_N440K": 0.5051740357478833, "Spike_N501Y": 0.587958607714017, "Spike_P681R": 0.1077140169332079, "Spike_Q493R": 0.5884289746001882, "Spike_Q498R": 0.587958607714017, "Spike_R346K": 0.08372530573847602, "Spike_S373P": 0.590310442144873, "Spike_S375F": 0.5856067732831609, "Spike_S477N": 0.5884289746001882, "Spike_T478K": 0.6975540921919097, "Spike_V143del": 0.8650047036688617, "Spike_V70del": 0.8607714016933208, "Spike_Y144del": 0.8645343367826905, "Spike_Y145H": 0.0, "Spike_Y505H": 0.5672624647224835, "country": "Brazil", "date": "2 Jan 2022", "date_range": "2 Jan-9 Jan 2022", "submissions": 2126.0}, {"Spike_D796Y": 0.9580144777662875, "Spike_E484A": 0.6597724922440538, "Spike_G339D": 0.9027921406411582, "Spike_G446S": 0.6070320579110652, "Spike_G496S": 0.6597724922440538, "Spike_H69del": 0.9327817993795243, "Spike_K417N": 0.6616339193381593, "Spike_L452R": 0.0359875904860393, "Spike_N440K": 0.5112719751809721, "Spike_N501Y": 0.6624612202688728, "Spike_P681R": 0.03681489141675284, "Spike_Q493R": 0.6614270941054808, "Spike_Q498R": 0.6626680455015512, "Spike_R346K": 0.1327817993795243, "Spike_S373P": 0.693071354705274, "Spike_S375F": 0.6936918304033092, "Spike_S477N": 0.6603929679420889, "Spike_T478K": 0.6963805584281282, "Spike_V143del": 0.94870734229576, "Spike_V70del": 0.9329886246122027, "Spike_Y144del": 0.9489141675284385, "Spike_Y145H": 0.00020682523267838676, "Spike_Y505H": 0.6494312306101344, "country": "Brazil", "date": "9 Jan 2022", "date_range": "9 Jan-16 Jan 2022", "submissions": 4835.0}, {"Spike_D796Y": 0.9791327913279133, "Spike_E484A": 0.8100271002710027, "Spike_G339D": 0.9211382113821138, "Spike_G446S": 0.7037940379403794, "Spike_G496S": 0.8059620596205962, "Spike_H69del": 0.8699186991869918, "Spike_K417N": 0.6289972899728997, "Spike_L452R": 0.011924119241192412, "Spike_N440K": 0.6504065040650406, "Spike_N501Y": 0.8089430894308943, "Spike_P681R": 0.013279132791327914, "Spike_Q493R": 0.808130081300813, "Spike_Q498R": 0.8078590785907859, "Spike_R346K": 0.17533875338753388, "Spike_S373P": 0.8040650406504065, "Spike_S375F": 0.8040650406504065, "Spike_S477N": 0.8075880758807588, "Spike_T478K": 0.8186991869918699, "Spike_V143del": 0.897289972899729, "Spike_V70del": 0.8699186991869918, "Spike_Y144del": 0.8975609756097561, "Spike_Y145H": 0.0, "Spike_Y505H": 0.8021680216802168, "country": "Brazil", "date": "16 Jan 2022", "date_range": "16 Jan-23 Jan 2022", "submissions": 3690.0}, {"Spike_D796Y": 0.9937050359712231, "Spike_E484A": 0.8156474820143885, "Spike_G339D": 0.9366007194244604, "Spike_G446S": 0.6955935251798561, "Spike_G496S": 0.8062050359712231, "Spike_H69del": 0.8651079136690647, "Spike_K417N": 0.5035971223021583, "Spike_L452R": 0.005845323741007194, "Spike_N440K": 0.6560251798561151, "Spike_N501Y": 0.8192446043165468, "Spike_P681R": 0.0049460431654676255, "Spike_Q493R": 0.8080035971223022, "Spike_Q498R": 0.8192446043165468, "Spike_R346K": 0.1596223021582734, "Spike_S373P": 0.7837230215827338, "Spike_S375F": 0.7823741007194245, "Spike_S477N": 0.8156474820143885, "Spike_T478K": 0.8205935251798561, "Spike_V143del": 0.920863309352518, "Spike_V70del": 0.8651079136690647, "Spike_Y144del": 0.920863309352518, "Spike_Y145H": 0.0, "Spike_Y505H": 0.8165467625899281, "country": "Brazil", "date": "23 Jan 2022", "date_range": "23 Jan-30 Jan 2022", "submissions": 2224.0}, {"Spike_D796Y": 0.9941884599418847, "Spike_E484A": 0.800747198007472, "Spike_G339D": 0.9468659194686592, "Spike_G446S": 0.7617268576172685, "Spike_G496S": 0.7911996679119967, "Spike_H69del": 0.9692818596928185, "Spike_K417N": 0.721876297218763, "Spike_L452R": 0.0037359900373599006, "Spike_N440K": 0.7251971772519717, "Spike_N501Y": 0.8019925280199253, "Spike_P681R": 0.0033208800332088003, "Spike_Q493R": 0.7982565379825654, "Spike_Q498R": 0.800747198007472, "Spike_R346K": 0.1656288916562889, "Spike_S373P": 0.8019925280199253, "Spike_S375F": 0.8073889580738896, "Spike_S477N": 0.8019925280199253, "Spike_T478K": 0.8044831880448319, "Spike_V143del": 0.9846409298464093, "Spike_V70del": 0.9692818596928185, "Spike_Y144del": 0.9842258198422582, "Spike_Y145H": 0.0, "Spike_Y505H": 0.7916147779161478, "country": "Brazil", "date": "30 Jan 2022", "date_range": "30 Jan-6 Feb 2022", "submissions": 2409.0}, {"Spike_D796Y": 0.9923664122137404, "Spike_E484A": 0.6215347529128163, "Spike_G339D": 0.8537565287263962, "Spike_G446S": 0.5821615106468461, "Spike_G496S": 0.6046605062274005, "Spike_H69del": 0.9819204499799116, "Spike_K417N": 0.5825632784250703, "Spike_L452R": 0.005222981116914423, "Spike_N440K": 0.506629168340699, "Spike_N501Y": 0.6118923262354359, "Spike_P681R": 0.0024106066693451184, "Spike_Q493R": 0.620731217356368, "Spike_Q498R": 0.6086781840096425, "Spike_R346K": 0.18200080353555645, "Spike_S373P": 0.6351948573724387, "Spike_S375F": 0.6432302129369225, "Spike_S477N": 0.6203294495781438, "Spike_T478K": 0.6223382884692648, "Spike_V143del": 0.9867416633186018, "Spike_V70del": 0.9819204499799116, "Spike_Y144del": 0.9867416633186018, "Spike_Y145H": 0.0, "Spike_Y505H": 0.5946163117717959, "country": "Brazil", "date": "6 Feb 2022", "date_range": "6 Feb-13 Feb 2022", "submissions": 2489.0}, {"Spike_D796Y": 0.9981354878806712, "Spike_E484A": 0.6003729024238658, "Spike_G339D": 0.853325046612803, "Spike_G446S": 0.545680546923555, "Spike_G496S": 0.5860783095090119, "Spike_H69del": 0.9620882535736482, "Spike_K417N": 0.6737103791174642, "Spike_L452R": 0.001243008079552517, "Spike_N440K": 0.5003107520198882, "Spike_N501Y": 0.5935363579863269, "Spike_P681R": 0.001243008079552517, "Spike_Q493R": 0.6072094468614045, "Spike_Q498R": 0.5954008701056557, "Spike_R346K": 0.24052206339341206, "Spike_S373P": 0.675574891236793, "Spike_S375F": 0.7022995649471722, "Spike_S477N": 0.6003729024238658, "Spike_T478K": 0.5991298943443132, "Spike_V143del": 0.9863269111249223, "Spike_V70del": 0.9620882535736482, "Spike_Y144del": 0.9863269111249223, "Spike_Y145H": 0.0, "Spike_Y505H": 0.5581106277190802, "country": "Brazil", "date": "13 Feb 2022", "date_range": "13 Feb-20 Feb 2022", "submissions": 1609.0}, {"Spike_D796Y": 0.9961649089165868, "Spike_E484A": 0.6327900287631831, "Spike_G339D": 0.8820709491850431, "Spike_G446S": 0.5819750719079578, "Spike_G496S": 0.5982742090124641, "Spike_H69del": 0.9578139980824545, "Spike_K417N": 0.7094918504314478, "Spike_L452R": 0.0, "Spike_N440K": 0.49760306807286675, "Spike_N501Y": 0.6078619367209971, "Spike_P681R": 0.0, "Spike_Q493R": 0.6241610738255033, "Spike_Q498R": 0.6145733461169702, "Spike_R346K": 0.24928092042186, "Spike_S373P": 0.7583892617449665, "Spike_S375F": 0.7746883988494727, "Spike_S477N": 0.6279961649089166, "Spike_T478K": 0.6222435282837967, "Spike_V143del": 0.9837008628954937, "Spike_V70del": 0.9568552253116012, "Spike_Y144del": 0.9827420901246404, "Spike_Y145H": 0.0, "Spike_Y505H": 0.576222435282838, "country": "Brazil", "date": "20 Feb 2022", "date_range": "20 Feb-27 Feb 2022", "submissions": 1043.0}, {"Spike_D796Y": 0.9987146529562982, "Spike_E484A": 0.6105398457583547, "Spike_G339D": 0.8650385604113111, "Spike_G446S": 0.5141388174807198, "Spike_G496S": 0.570694087403599, "Spike_H69del": 0.9588688946015425, "Spike_K417N": 0.7005141388174807, "Spike_L452R": 0.0, "Spike_N440K": 0.4241645244215938, "Spike_N501Y": 0.5925449871465296, "Spike_P681R": 0.0, "Spike_Q493R": 0.6041131105398457, "Spike_Q498R": 0.5938303341902313, "Spike_R346K": 0.30848329048843187, "Spike_S373P": 0.7300771208226221, "Spike_S375F": 0.7390745501285347, "Spike_S477N": 0.6015424164524421, "Spike_T478K": 0.5989717223650386, "Spike_V143del": 0.9550128534704371, "Spike_V70del": 0.9588688946015425, "Spike_Y144del": 0.9550128534704371, "Spike_Y145H": 0.0, "Spike_Y505H": 0.5578406169665809, "country": "Brazil", "date": "27 Feb 2022", "date_range": "27 Feb-6 Mar 2022", "submissions": 778.0}, {"Spike_D796Y": 1.0, "Spike_E484A": 0.29596412556053814, "Spike_G339D": 0.7713004484304933, "Spike_G446S": 0.2062780269058296, "Spike_G496S": 0.25112107623318386, "Spike_H69del": 0.9282511210762332, "Spike_K417N": 0.47533632286995514, "Spike_L452R": 0.0, "Spike_N440K": 0.21076233183856502, "Spike_N501Y": 0.29596412556053814, "Spike_P681R": 0.0, "Spike_Q493R": 0.30493273542600896, "Spike_Q498R": 0.2914798206278027, "Spike_R346K": 0.2556053811659193, "Spike_S373P": 0.4484304932735426, "Spike_S375F": 0.47533632286995514, "Spike_S477N": 0.2914798206278027, "Spike_T478K": 0.29596412556053814, "Spike_V143del": 0.9327354260089686, "Spike_V70del": 0.9237668161434978, "Spike_Y144del": 0.9327354260089686, "Spike_Y145H": 0.0, "Spike_Y505H": 0.2600896860986547, "country": "Brazil", "date": "6 Mar 2022", "date_range": "6 Mar-13 Mar 2022", "submissions": 223.0}]